Workbook

Sheet Cover
B6: STATE BANK OF INDIA
B8: NSE: SBIN | BSE: 500112 | ISIN: INE062A01020
B10: INTEGRATED FINANCIAL MODEL
B11: Historical Financials (FY22A–FY26A) · Projections (FY27E–FY31E) · Valuation & Scenario Analysis
B14: Initiating Coverage — Equity Research Workflow
B15: Prepared: September 27, 2026
B18: CONTENTS
B19: 1. Assumptions — key operating & macro drivers (FY27E–FY31E)
B20: 2. Revenue Model — advances, deposits & income build by segment and geography
B21: 3. Income Statement — full P&L, FY22A–FY31E
B22: 4. Balance Sheet — full statement of assets & liabilities, FY22A–FY31E
B23: 5. Cash Flow Statement — operating / investing / financing activities
... B31: Color code: Blue = hardcoded input Black = formula Green = link to another sheet

Sheet Assumptions
A1: ASSUMPTIONS
A2: State Bank of India — Key operating & macro drivers. Blue cells are the only inputs to change.
A3: (₹ crore unless stated) | B3: FY22A | C3: FY23A | D3: FY24A | E3: FY25A | F3: FY26A | G3: FY27E | H3: FY28E | I3: FY29E | J3: FY30E | K3: FY31E
A4: GROWTH ASSUMPTIONS — ADVANCES & DEPOSITS
A5: Domestic Retail Advances Growth % | B5: 0.165 | C5: 0.17 | D5: 0.17 | E5: 0.17 | F5: 0.1539 | G5: 0.15 | H5: 0.14 | I5: 0.13 | J5: 0.125 | K5: 0.12
A6: Domestic Agriculture Advances Growth % | B6: 0.12 | C6: 0.12 | D6: 0.12 | E6: 0.12 | F6: 0.1968 | G6: 0.14 | H6: 0.13 | I6: 0.12 | J6: 0.11 | K6: 0.11
A7: Domestic SME Advances Growth % | B7: 0.16 | C7: 0.16 | D7: 0.16 | E7: 0.16 | F7: 0.2099 | G7: 0.17 | H7: 0.16 | I7: 0.15 | J7: 0.14 | K7: 0.13
A8: Domestic Corporate Advances Growth % | B8: 0.1 | C8: 0.133 | D8: 0.1222 | E8: -0.0064 | F8: 0.1483 | G8: 0.12 | H8: 0.12 | I8: 0.125 | J8: 0.13 | K8: 0.13
A9: Foreign Office Advances Growth % | B9: 0.1 | C9: 0.2676 | D9: 0.2545 | E9: 0.2582 | F9: 0.2001 | G9: 0.16 | H9: 0.15 | I9: 0.14 | J9: 0.13 | K9: 0.12
A10: Total Deposits Growth % | B10: 0.095 | C10: 0.1029 | D10: 0.1114 | E10: 0.0837 | F10: 0.1102 | G10: 0.12 | H10: 0.115 | I10: 0.115 | J10: 0.11 | K10: 0.11
A11: CASA Ratio (% of total deposits) | B11: 0.4533 | C11: 0.426 | D11: 0.408 | E11: 0.3997 | F11: 0.3946 | G11: 0.39 | H11: 0.387 | I11: 0.385 | J11: 0.385 | K11: 0.385
A13: YIELD & COST ASSUMPTIONS
A14: Yield on Domestic Advances % | B14: 0.073 | C14: 0.076 | D14: 0.079 | E14: 0.08 | F14: 0.079 | G14: 0.0795 | H14: 0.08 | I14: 0.0805 | J14: 0.0805 | K14: 0.0805
A15: Yield on Foreign Office Advances % | B15: 0.048 | C15: 0.051 | D15: 0.053 | E15: 0.054 | F15: 0.0545 | G15: 0.0545 | H15: 0.0545 | I15: 0.0545 | J15: 0.0545 | K15: 0.0545
A16: Yield on Investments (Treasury) % [calibrated to tie NII to disclosed actuals] | B16: 0.059 | C16: 0.0587 | D16: 0.0561 | E16: 0.0575 | F16: 0.0525 | G16: 0.056 | H16: 0.0575 | I16: 0.059 | J16: 0.06 | K16: 0.0605
A17: Cost of CASA Deposits % | B17: 0.023 | C17: 0.0245 | D17: 0.026 | E17: 0.027 | F17: 0.027 | G17: 0.027 | H17: 0.027 | I17: 0.0265 | J17: 0.0265 | K17: 0.0265
A18: Cost of Term Deposits % | B18: 0.055 | C18: 0.058 | D18: 0.0605 | E18: 0.064 | F18: 0.0655 | G18: 0.066 | H18: 0.065 | I18: 0.064 | J18: 0.064 | K18: 0.064
A19: Cost of Borrowings % | B19: 0.058 | C19: 0.062 | D19: 0.065 | E19: 0.067 | F19: 0.068 | G19: 0.068 | H19: 0.068 | I19: 0.0675 | J19: 0.0675 | K19: 0.0675
A21: FEE & OTHER INCOME ASSUMPTIONS
A22: Fee & Commission Income Growth % | B22: 0.08 | C22: 0.1296 | D22: 0.1362 | E22: 0.1293 | F22: 0.1285 | G22: 0.12 | H22: 0.12 | I22: 0.12 | J22: 0.12 | K22: 0.12
A23: Treasury / Trading Gains Growth % | B23: 0.1 | C23: 2.5789 | D23: 0.2059 | E23: 0.1098 | F23: 0.6264 | G23: -0.3 | H23: 0.08 | I23: 0.08 | J23: 0.08 | K23: 0.08
A24: Forex Income Growth % | B24: 0.08 | C24: 0.125 | D24: 0.1481 | E24: 0.1613 | F24: 1.3056 | G24: -0.35 | H24: 0.08 | I24: 0.08 | J24: 0.08 | K24: 0.08
A25: Dividend from Subsidiaries Growth % | B25: 0.1 | C25: 0.2381 | D25: 0.2308 | E25: 0.2188 | F25: 0.1795 | G25: 0.1 | H25: 0.1 | I25: 0.1 | J25: 0.1 | K25: 0.1
A26: One-off / Exceptional Non-Interest Income (Yes Bank & Jio Payments Bank stake sale gains, FY26 only) | B26: 0 | C26: 0 | D26: 0 | E26: 0 | F26: 4618 | G26: 0 | H26: 0 | I26: 0 | J26: 0 | K26: 0
A28: OPERATING COST ASSUMPTIONS
A29: Employee Cost Growth % | B29: 0.06 | C29: 0.0718 | D29: 0.2472 | E29: -0.0754 | F29: 0.101 | G29: 0.08 | H29: 0.08 | I29: 0.08 | J29: 0.08 | K29: 0.08
A30: Other Operating Expenses Growth % (rent, D&A, admin, tech) | B30: 0.09 | C30: 0.4886 | D30: -0.1629 | E30: 0.1911 | F30: 0.1303 | G30: 0.11 | H30: 0.11 | I30: 0.11 | J30: 0.1 | K30: 0.1
A32: ASSET QUALITY & CAPITAL ASSUMPTIONS
A33: Credit Cost % (loan loss provisions / avg. gross advances) | B33: 0.0068 | C33: 0.0046 | D33: 0.0032 | E33: 0.0026 | F33: 0.0023 | G33: 0.0042 | H33: 0.0042 | I33: 0.0045 | J33: 0.0045 | K33: 0.0045
A34: Gross NPA Ratio % (guided) | B34: 0.0397 | C34: 0.0278 | D34: 0.0224 | E34: 0.0182 | F34: 0.0149 | G34: 0.0145 | H34: 0.0142 | I34: 0.014 | J34: 0.014 | K34: 0.014
A35: Net NPA Ratio % (guided) | B35: 0.0102 | C35: 0.0067 | D35: 0.0057 | E35: 0.0047 | F35: 0.0039 | G35: 0.0038 | H35: 0.0037 | I35: 0.0036 | J35: 0.0036 | K35: 0.0036
A36: Provision Coverage Ratio % | B36: 0.753 | C36: 0.768 | D36: 0.755 | E36: 0.7442 | F36: 0.7436 | G36: 0.745 | H36: 0.745 | I36: 0.745 | J36: 0.745 | K36: 0.745
A37: Capital Adequacy Ratio (CAR) target % | B37: 0.1383 | C37: 0.1468 | D37: 0.1428 | E37: 0.1425 | F37: 0.154 | G37: 0.152 | H37: 0.153 | I37: 0.154 | J37: 0.154 | K37: 0.155
A39: TAX & CAPITAL RETURN ASSUMPTIONS
A40: Effective Tax Rate % | B40: 0.32 | C40: 0.253 | D40: 0.252 | E40: 0.252 | F40: 0.252 | G40: 0.252 | H40: 0.252 | I40: 0.252 | J40: 0.252 | K40: 0.252
A41: Dividend Payout Ratio % | B41: 0.2 | C41: 0.2008 | D41: 0.2002 | E41: 0.2001 | F41: 0.1971 | G41: 0.215 | H41: 0.215 | I41: 0.215 | J41: 0.215 | K41: 0.215
A42: Basic Shares Outstanding growth % (dilution) | B42: 0 | C42: 0 | D42: 0 | E42: 0 | F42: 0.0188 | G42: 0 | H42: 0 | I42: 0 | J42: 0 | K42: 0

Sheet Revenue Model
A1: REVENUE MODEL
A2: State Bank of India — Advances, deposits & income build by segment and geography
A3: (₹ crore unless stated) | B3: FY22A | C3: FY23A | D3: FY24A | E3: FY25A | F3: FY26A | G3: FY27E | H3: FY28E | I3: FY29E | J3: FY30E | K3: FY31E
A4: A. DOMESTIC ADVANCES & INTEREST INCOME BY SEGMENT
A5: Retail Advances
A6: Home Loans — Balance | B6: 564181 | C6: 660092 | D6: 772307 | E6: 903600 | F6: 1042640 | G6: =F6*(1+Assumptions!G5) -> 1199036 | H6: =G6*(1+Assumptions!H5) -> 1366901 | I6: =H6*(1+Assumptions!I5) -> 1544598.2 | J6: =I6*(1+Assumptions!J5) -> 1737672.9 | K6: =J6*(1+Assumptions!K5) -> 1946193.7
A7: Auto Loans — Balance | B7: 47015 | C7: 55008 | D7: 64359 | E7: 75300 | F7: 86887 | G7: =F7*(1+Assumptions!G5) -> 99920.05 | H7: =G7*(1+Assumptions!H5) -> 113908.86 | I7: =H7*(1+Assumptions!I5) -> 128717.01 | J7: =I7*(1+Assumptions!J5) -> 144806.63 | K7: =J7*(1+Assumptions!K5) -> 162183.43
A8: Other Retail (Personal / Gold / Education) — Balance | B8: 329106 | C8: 385053 | D8: 450513 | E8: 527100 | F8: 608206 | G8: =F8*(1+Assumptions!G5) -> 699436.9 | H8: =G8*(1+Assumptions!H5) -> 797358.07 | I8: =H8*(1+Assumptions!I5) -> 901014.61 | J8: =I8*(1+Assumptions!J5) -> 1013641.4 | K8: =J8*(1+Assumptions!K5) -> 1135278.4
A9: Total Retail Advances | B9: =B6+B7+B8 -> 940302 | C9: =C6+C7+C8 -> 1100153 | D9: =D6+D7+D8 -> 1287179 | E9: =E6+E7+E8 -> 1506000 | F9: =F6+F7+F8 -> 1737733 | G9: =G6+G7+G8 -> 1998392.9 | H9: =H6+H7+H8 -> 2278168 | I9: =I6+I7+I8 -> 2574329.8 | ... K9: =K6+K7+K8 -> 3243655.5
A10: Retail Advances YoY Growth % | B10: n/a | C10: =C9/B9-1 -> 0.16999964 | D10: =D9/C9-1 -> 0.16999999 | E10: =E9/D9-1 -> 0.17000044 | F10: =F9/E9-1 -> 0.15387317 | G10: =G9/F9-1 -> 0.15 | H10: =H9/G9-1 -> 0.14 | I10: =I9/H9-1 -> 0.13 | J10: =J9/I9-1 -> 0.125 | K10: =K9/J9-1 -> 0.12
A11: Retail Interest Income (avg. blended yield, via Domestic Yield) | B11: =B9*Assumptions!B14 -> 68642.046 | C11: =C9*Assumptions!C14 -> 83611.628 | D11: =D9*Assumptions!D14 -> 101687.14 | E11: =E9*Assumptions!E14 -> 120480 | F11: =F9*Assumptions!F14 -> 137280.91 | G11: =G9*Assumptions!G14 -> 158872.24 | H11: =H9*Assumptions!H14 -> 182253.44 | I11: =I9*Assumptions!I14 -> 207233.55 | ... K11: =K9*Assumptions!K14 -> 261114.27
A12: Agriculture Advances
A13: Agriculture & Allied Activities — Balance | B13: 230745 | C13: 258434 | D13: 289446 | E13: 324180 | F13: 387979 | G13: =F13*(1+Assumptions!G6) -> 442296.06 | H13: =G13*(1+Assumptions!H6) -> 499794.55 | I13: =H13*(1+Assumptions!I6) -> 559769.89 | J13: =I13*(1+Assumptions!J6) -> 621344.58 | K13: =J13*(1+Assumptions!K6) -> 689692.49
A14: Agriculture Interest Income | B14: =B13*Assumptions!B14 -> 16844.385 | C14: =C13*Assumptions!C14 -> 19640.984 | D14: =D13*Assumptions!D14 -> 22866.234 | E14: =E13*Assumptions!E14 -> 25934.4 | F14: =F13*Assumptions!F14 -> 30650.341 | G14: =G13*Assumptions!G14 -> 35162.537 | H14: =H13*Assumptions!H14 -> 39983.564 | I14: =I13*Assumptions!I14 -> 45061.476 | ... K14: =K13*Assumptions!K14 -> 55520.245
A15: SME Advances
A16: Small & Medium Enterprises — Balance | B16: 299994 | C16: 347993 | D16: 403672 | E16: 468260 | F16: 566548 | G16: =F16*(1+Assumptions!G7) -> 662861.16 | H16: =G16*(1+Assumptions!H7) -> 768918.95 | I16: =H16*(1+Assumptions!I7) -> 884256.79 | J16: =I16*(1+Assumptions!J7) -> 1008052.7 | K16: =J16*(1+Assumptions!K7) -> 1139099.6
A17: SME Interest Income | B17: =B16*Assumptions!B14 -> 21899.562 | C17: =C16*Assumptions!C14 -> 26447.468 | D17: =D16*Assumptions!D14 -> 31890.088 | E17: =E16*Assumptions!E14 -> 37460.8 | F17: =F16*Assumptions!F14 -> 44757.292 | G17: =G16*Assumptions!G14 -> 52697.462 | H17: =H16*Assumptions!H14 -> 61513.516 | I17: =I16*Assumptions!I14 -> 71182.671 | ... K17: =K16*Assumptions!K14 -> 91697.517
A18: Corporate Advances
A19: Large Corporate & Commercial — Balance | B19: 1031911 | C19: 1169172 | D19: 1312018 | E19: 1303560 | F19: 1496878 | G19: =F19*(1+Assumptions!G8) -> 1676503.4 | H19: =G19*(1+Assumptions!H8) -> 1877683.8 | I19: =H19*(1+Assumptions!I8) -> 2112394.2 | J19: =I19*(1+Assumptions!J8) -> 2387005.5 | K19: =J19*(1+Assumptions!K8) -> 2697316.2
A20: Corporate Interest Income | B20: =B19*Assumptions!B14 -> 75329.503 | C20: =C19*Assumptions!C14 -> 88857.072 | D20: =D19*Assumptions!D14 -> 103649.42 | E20: =E19*Assumptions!E14 -> 104284.8 | F20: =F19*Assumptions!F14 -> 118253.36 | G20: =G19*Assumptions!G14 -> 133282.02 | H20: =H19*Assumptions!H14 -> 150214.7 | I20: =I19*Assumptions!I14 -> 170047.74 | ... K20: =K19*Assumptions!K14 -> 217133.95
A21: TOTAL DOMESTIC ADVANCES | B21: =B9+B13+B16+B19 -> 2502952 | C21: =C9+C13+C16+C19 -> 2875752 | D21: =D9+D13+D16+D19 -> 3292315 | E21: =E9+E13+E16+E19 -> 3602000 | F21: =F9+F13+F16+F19 -> 4189138 | G21: =G9+G13+G16+G19 -> 4780053.5 | H21: =H9+H13+H16+H19 -> 5424565.2 | I21: =I9+I13+I16+I19 -> 6130750.7 | ... K21: =K9+K13+K16+K19 -> 7769763.8
A22: Domestic Advances YoY Growth % | B22: n/a | C22: =C21/B21-1 -> 0.14894413 | D22: =D21/C21-1 -> 0.14485359 | E22: =E21/D21-1 -> 0.094062992 | F22: =F21/E21-1 -> 0.16300333 | G22: =G21/F21-1 -> 0.14105898 | H22: =H21/G21-1 -> 0.13483357 | I22: =I21/H21-1 -> 0.13018287 | J22: =J21/I21-1 -> 0.1275167 | K22: =K21/J21-1 -> 0.12401259
A23: Total Domestic Interest Income on Advances | B23: =B11+B14+B17+B20 -> 182715.5 | C23: =C11+C14+C17+C20 -> 218557.15 | D23: =D11+D14+D17+D20 -> 260092.89 | E23: =E11+E14+E17+E20 -> 288160 | F23: =F11+F14+F17+F20 -> 330941.9 | G23: =G11+G14+G17+G20 -> 380014.26 | H23: =H11+H14+H17+H20 -> 433965.22 | I23: =I11+I14+I17+I20 -> 493525.43 | ... K23: =K11+K14+K17+K20 -> 625465.99
A25: B. INTERNATIONAL (FOREIGN OFFICE) ADVANCES
A26: Foreign Office Advances — Balance | B26: 309354 | C26: 392148 | D26: 491955 | E26: 619000 | F26: 742862 | G26: =F26*(1+Assumptions!G9) -> 861719.92 | H26: =G26*(1+Assumptions!H9) -> 990977.91 | I26: =H26*(1+Assumptions!I9) -> 1129714.8 | J26: =I26*(1+Assumptions!J9) -> 1276577.7 | K26: =J26*(1+Assumptions!K9) -> 1429767.1
A27: Foreign Office Interest Income | B27: =B26*Assumptions!B15 -> 14848.992 | C27: =C26*Assumptions!C15 -> 19999.548 | D27: =D26*Assumptions!D15 -> 26073.615 | E27: =E26*Assumptions!E15 -> 33426 | F27: =F26*Assumptions!F15 -> 40485.979 | G27: =G26*Assumptions!G15 -> 46963.736 | H27: =H26*Assumptions!H15 -> 54008.296 | I27: =I26*Assumptions!I15 -> 61569.457 | ... K27: =K26*Assumptions!K15 -> 77922.305
A28: TOTAL GROSS ADVANCES (WHOLE BANK) | B28: =B21+B26 -> 2812306 | C28: =C21+C26 -> 3267900 | D28: =D21+D26 -> 3784270 | E28: =E21+E26 -> 4221000 | F28: =F21+F26 -> 4932000 | G28: =G21+G26 -> 5641773.5 | H28: =H21+H26 -> 6415543.1 | I28: =I21+I26 -> 7260465.5 | ... K28: =K21+K26 -> 9199530.9
A29: Total Advances YoY Growth % | B29: n/a | C29: =C28/B28-1 -> 0.16200015 | D29: =D28/C28-1 -> 0.15801279 | E29: =E28/D28-1 -> 0.11540667 | F29: =F28/E28-1 -> 0.1684435 | G29: =G28/F28-1 -> 0.14391189 | H29: =H28/G28-1 -> 0.13715008 | I29: =I28/H28-1 -> 0.13169928 | J29: =J28/I28-1 -> 0.1279031 | K29: =K28/J28-1 -> 0.12338708
A30: Blended Yield on Advances % (memo) | B30: =(B23+B27)/B28 -> 0.070249997 | C30: =(C23+C27)/C28 -> 0.073 | D30: =(D23+D27)/D28 -> 0.075620001 | E30: =(E23+E27)/E28 -> 0.076187159 | F30: =(F23+F27)/F28 -> 0.075309789 | G30: =(G23+G27)/G28 -> 0.07568152 | H30: =(H23+H27)/H28 -> 0.076061138 | I30: =(I23+I27)/I28 -> 0.076454449 | ... K30: =(K23+K27)/K28 -> 0.076459148
A31: TOTAL INTEREST INCOME ON ADVANCES | B31: =B23+B27 -> 197564.49 | C31: =C23+C27 -> 238556.7 | D31: =D23+D27 -> 286166.5 | E31: =E23+E27 -> 321586 | F31: =F23+F27 -> 371427.88 | G31: =G23+G27 -> 426977.99 | H31: =H23+H27 -> 487973.51 | I31: =I23+I27 -> 555094.89 | ... K31: =K23+K27 -> 703388.29
A33: C. INVESTMENTS & OTHER INTEREST INCOME
A34: Investment Book (SLR + Non-SLR) — Balance | B34: 1620000 | C34: 1913110 | D34: 2110550 | E34: 2205600 | F34: 2340000 | G34: =F34*(1+Assumptions!G10*0.85) -> 2578680 | H34: =G34*(1+Assumptions!H10*0.85) -> 2830746 | I34: =H34*(1+Assumptions!I10*0.85) -> 3107451.4 | J34: =I34*(1+Assumptions!J10*0.85) -> 3397998.1 | K34: =J34*(1+Assumptions!K10*0.85) -> 3715710.9
A35: Interest Income on Investments | B35: =B34*Assumptions!B16 -> 95580 | C35: =C34*Assumptions!C16 -> 112299.56 | D35: =D34*Assumptions!D16 -> 118401.85 | E35: =E34*Assumptions!E16 -> 126822 | F35: =F34*Assumptions!F16 -> 122850 | G35: =G34*Assumptions!G16 -> 144406.08 | H35: =H34*Assumptions!H16 -> 162767.89 | I35: =I34*Assumptions!I16 -> 183339.63 | ... K35: =K34*Assumptions!K16 -> 224800.51
A36: Interest on Balances with RBI / Other Banks | B36: 4200 | C36: 4500 | D36: 4900 | E36: 5300 | F36: 6100 | G36: =F36*1.08 -> 6588 | H36: =G36*1.08 -> 7115.04 | I36: =H36*1.08 -> 7684.2432 | J36: =I36*1.08 -> 8298.9827 | K36: =J36*1.08 -> 8962.9013
A37: TOTAL INTEREST INCOME | B37: =B31+B35+B36 -> 297344.49 | C37: =C31+C35+C36 -> 355356.26 | D37: =D31+D35+D36 -> 409468.35 | E37: =E31+E35+E36 -> 453708 | F37: =F31+F35+F36 -> 500377.88 | G37: =G31+G35+G36 -> 577972.07 | H37: =H31+H35+H36 -> 657856.45 | I37: =I31+I35+I36 -> 746118.76 | ... K37: =K31+K35+K36 -> 937151.7
A39: D. DEPOSITS & INTEREST EXPENSE
A40: Total Deposits — Balance | B40: 4051534 | C40: 4468540 | D40: 4966540 | E40: 5382000 | F40: 5975000 | G40: =F40*(1+Assumptions!G10) -> 6692000 | H40: =G40*(1+Assumptions!H10) -> 7461580 | I40: =H40*(1+Assumptions!I10) -> 8319661.7 | J40: =I40*(1+Assumptions!J10) -> 9234824.5 | K40: =J40*(1+Assumptions!K10) -> 10250655
A41: Total Deposits YoY Growth % | B41: n/a | C41: =C40/B40-1 -> 0.10292546 | D41: =D40/C40-1 -> 0.1114458 | E41: =E40/D40-1 -> 0.083651798 | F41: =F40/E40-1 -> 0.11018209 | G41: =G40/F40-1 -> 0.12 | H41: =H40/G40-1 -> 0.115 | I41: =I40/H40-1 -> 0.115 | J41: =J40/I40-1 -> 0.11 | K41: =K40/J40-1 -> 0.11
A42: CASA Deposits — Balance | B42: 1836560 | C42: 1903598 | D42: 2026348 | E42: 2151185 | F42: 2357735 | G42: =G40*Assumptions!G11 -> 2609880 | H42: =H40*Assumptions!H11 -> 2887631.5 | I42: =I40*Assumptions!I11 -> 3203069.8 | J42: =J40*Assumptions!J11 -> 3555407.4 | K42: =K40*Assumptions!K11 -> 3946502.2
A43: Term Deposits — Balance | B43: 2214974 | C43: 2564942 | D43: 2940192 | E43: 3230815 | F43: 3617265 | G43: =G40-G42 -> 4082120 | H43: =H40-H42 -> 4573948.5 | I43: =I40-I42 -> 5116591.9 | J43: =J40-J42 -> 5679417.1 | K43: =K40-K42 -> 6304152.9
A44: CASA Ratio % (memo, ties to Assumptions) | B44: =B42/B40 -> 0.45329991 | C44: =C42/C40 -> 0.42599999 | D44: =D42/D40 -> 0.40799994 | E44: =E42/E40 -> 0.39969993 | F44: =F42/F40 -> 0.3946 | G44: =G42/G40 -> 0.39 | H44: =H42/H40 -> 0.387 | I44: =I42/I40 -> 0.385 | ... K44: =K42/K40 -> 0.385
A45: CASA Interest Expense | B45: =B42*Assumptions!B17 -> 42240.88 | C45: =C42*Assumptions!C17 -> 46638.151 | D45: =D42*Assumptions!D17 -> 52685.048 | E45: =E42*Assumptions!E17 -> 58081.995 | F45: =F42*Assumptions!F17 -> 63658.845 | G45: =G42*Assumptions!G17 -> 70466.76 | H45: =H42*Assumptions!H17 -> 77966.049 | I45: =I42*Assumptions!I17 -> 84881.348 | ... K45: =K42*Assumptions!K17 -> 104582.31
A46: Term Deposit Interest Expense | B46: =B43*Assumptions!B18 -> 121823.57 | C46: =C43*Assumptions!C18 -> 148766.64 | D46: =D43*Assumptions!D18 -> 177881.62 | E46: =E43*Assumptions!E18 -> 206772.16 | F46: =F43*Assumptions!F18 -> 236930.86 | G46: =G43*Assumptions!G18 -> 269419.92 | H46: =H43*Assumptions!H18 -> 297306.66 | I46: =I43*Assumptions!I18 -> 327461.88 | ... K46: =K43*Assumptions!K18 -> 403465.79
A47: Total Interest Expense on Deposits | B47: =B45+B46 -> 164064.45 | C47: =C45+C46 -> 195404.79 | D47: =D45+D46 -> 230566.66 | E47: =E45+E46 -> 264854.16 | F47: =F45+F46 -> 300589.7 | G47: =G45+G46 -> 339886.68 | H47: =H45+H46 -> 375272.7 | I47: =I45+I46 -> 412343.23 | ... K47: =K45+K46 -> 508048.1
A48: Interest Expense on Borrowings | B48: 230000 | C48: 258000 | D48: 290000 | E48: 327000 | F48: 382000 | G48: =F48*1.12 -> 427840 | H48: =G48*1.12 -> 479180.8 | I48: =H48*1.12 -> 536682.5 | J48: =I48*1.12 -> 601084.4 | K48: =J48*1.12 -> 673214.52
A49: Borrowings Interest Expense | B49: =B48*Assumptions!B19 -> 13340 | C49: =C48*Assumptions!C19 -> 15996 | D49: =D48*Assumptions!D19 -> 18850 | E49: =E48*Assumptions!E19 -> 21909 | F49: =F48*Assumptions!F19 -> 25976 | G49: =G48*Assumptions!G19 -> 29093.12 | H49: =H48*Assumptions!H19 -> 32584.294 | I49: =I48*Assumptions!I19 -> 36226.068 | ... K49: =K48*Assumptions!K19 -> 45441.98
A50: TOTAL INTEREST EXPENSE | B50: =B47+B49 -> 177404.45 | C50: =C47+C49 -> 211400.79 | D50: =D47+D49 -> 249416.66 | E50: =E47+E49 -> 286763.16 | F50: =F47+F49 -> 326565.7 | G50: =G47+G49 -> 368979.8 | H50: =H47+H49 -> 407857 | I50: =I47+I49 -> 448569.3 | ... K50: =K47+K49 -> 553490.08
A52: NET INTEREST INCOME (NII) | B52: =B37-B50 -> 119940.04 | C52: =C37-C50 -> 143955.47 | D52: =D37-D50 -> 160051.69 | E52: =E37-E50 -> 166944.85 | F52: =F37-F50 -> 173812.18 | G52: =G37-G50 -> 208992.27 | H52: =H37-H50 -> 249999.45 | I52: =I37-I50 -> 297549.46 | ... K52: =K37-K50 -> 383661.63
A53: NII YoY Growth % | B53: n/a | C53: =C52/B52-1 -> 0.20022865 | D53: =D52/C52-1 -> 0.11181389 | E53: =E52/D52-1 -> 0.043068298 | F53: =F52/E52-1 -> 0.041135343 | G53: =G52/F52-1 -> 0.20240292 | H53: =H52/G52-1 -> 0.19621384 | I53: =I52/H52-1 -> 0.19020048 | J53: =J52/I52-1 -> 0.1424532 | K53: =K52/J52-1 -> 0.12862788
A54: Domestic Net Interest Margin % (memo, NII / avg. domestic advances) | B54: =B52/B21 -> 0.047919432 | C54: =C52/C21 -> 0.050058374 | D54: =D52/D21 -> 0.048613723 | E54: =E52/E21 -> 0.046347819 | F54: =F52/F21 -> 0.041491156 | G54: =G52/G21 -> 0.043721743 | H54: =H52/H21 -> 0.046086541 | I54: =I52/I21 -> 0.048533936 | ... K54: =K52/K21 -> 0.049378802
A56: E. NON-INTEREST INCOME
A57: Fee, Commission & Brokerage Income | B57: 24700 | C57: 27900 | D57: 31700 | E57: 35800 | F57: 40400 | G57: =F57*(1+Assumptions!G22) -> 45248 | H57: =G57*(1+Assumptions!H22) -> 50677.76 | I57: =H57*(1+Assumptions!I22) -> 56759.091 | J57: =I57*(1+Assumptions!J22) -> 63570.182 | K57: =J57*(1+Assumptions!K22) -> 71198.604
A58: Fee Income YoY Growth % | B58: n/a | C58: =C57/B57-1 -> 0.12955466 | D58: =D57/C57-1 -> 0.13620072 | E58: =E57/D57-1 -> 0.12933754 | F58: =F57/E57-1 -> 0.12849162 | G58: =G57/F57-1 -> 0.12 | H58: =H57/G57-1 -> 0.12 | I58: =I57/H57-1 -> 0.12 | J58: =J57/I57-1 -> 0.12 | K58: =K57/J57-1 -> 0.12
A59: Treasury / Trading Gains | B59: 1900 | C59: 6800 | D59: 8200 | E59: 9100 | F59: 14800 | G59: =F59*(1+Assumptions!G23) -> 10360 | H59: =G59*(1+Assumptions!H23) -> 11188.8 | I59: =H59*(1+Assumptions!I23) -> 12083.904 | J59: =I59*(1+Assumptions!J23) -> 13050.616 | K59: =J59*(1+Assumptions!K23) -> 14094.666
A60: Forex Income | B60: 2400 | C60: 2700 | D60: 3100 | E60: 3600 | F60: 8300 | G60: =F60*(1+Assumptions!G24) -> 5395 | H60: =G60*(1+Assumptions!H24) -> 5826.6 | I60: =H60*(1+Assumptions!I24) -> 6292.728 | J60: =I60*(1+Assumptions!J24) -> 6796.1462 | K60: =J60*(1+Assumptions!K24) -> 7339.8379
A61: Dividend Income from Subsidiaries | B61: 2100 | C61: 2600 | D61: 3200 | E61: 3900 | F61: 4600 | G61: =F61*(1+Assumptions!G25) -> 5060 | H61: =G61*(1+Assumptions!H25) -> 5566 | I61: =H61*(1+Assumptions!I25) -> 6122.6 | J61: =I61*(1+Assumptions!J25) -> 6734.86 | K61: =J61*(1+Assumptions!K25) -> 7408.346
A62: Recovery from Written-off Accounts | B62: 7200 | C62: 6500 | D62: 6100 | E62: 5700 | F62: 5200 | G62: =F62*0.97 -> 5044 | H62: =G62*0.97 -> 4892.68 | I62: =H62*0.97 -> 4745.8996 | J62: =I62*0.97 -> 4603.5226 | K62: =J62*0.97 -> 4465.4169
A63: Other Miscellaneous Income | B63: 3500 | C63: 3700 | D63: 4000 | E63: 4300 | F63: 4600 | G63: =F63*1.08 -> 4968 | H63: =G63*1.08 -> 5365.44 | I63: =H63*1.08 -> 5794.6752 | J63: =I63*1.08 -> 6258.2492 | K63: =J63*1.08 -> 6758.9092
A64: One-off / Exceptional Items (Yes Bank & Jio Payments Bank stake sale, FY26) | B64: =Assumptions!B26 -> 0 | C64: =Assumptions!C26 -> 0 | D64: =Assumptions!D26 -> 0 | E64: =Assumptions!E26 -> 0 | F64: =Assumptions!F26 -> 4618 | G64: =Assumptions!G26 -> 0 | H64: =Assumptions!H26 -> 0 | I64: =Assumptions!I26 -> 0 | ... K64: =Assumptions!K26 -> 0
A65: TOTAL NON-INTEREST INCOME | B65: =B57+B59+B60+B61+B62+B63+B64 -> 41800 | C65: =C57+C59+C60+C61+C62+C63+C64 -> 50200 | D65: =D57+D59+D60+D61+D62+D63+D64 -> 56300 | E65: =E57+E59+E60+E61+E62+E63+E64 -> 62400 | F65: =F57+F59+F60+F61+F62+F63+F64 -> 82518 | G65: =G57+G59+G60+G61+G62+G63+G64 -> 76075 | H65: =H57+H59+H60+H61+H62+H63+H64 -> 83517.28 | I65: =I57+I59+I60+I61+I62+I63+I64 -> 91798.898 | ... K65: =K57+K59+K60+K61+K62+K63+K64 -> 111265.78
A66: TOTAL NET REVENUE (NII + Non-Interest Income) | B66: =B52+B65 -> 161740.04 | C66: =C52+C65 -> 194155.47 | D66: =D52+D65 -> 216351.69 | E66: =E52+E65 -> 229344.85 | F66: =F52+F65 -> 256330.18 | G66: =G52+G65 -> 285067.27 | H66: =H52+H65 -> 333516.73 | I66: =I52+I65 -> 389348.36 | ... K66: =K52+K65 -> 494927.41
A67: Total Net Revenue YoY Growth % | B67: n/a | C67: =C66/B66-1 -> 0.20041687 | D67: =D66/C66-1 -> 0.11432189 | E67: =E66/D66-1 -> 0.060055708 | F67: =F66/E66-1 -> 0.1176627 | G67: =G66/F66-1 -> 0.11210967 | H67: =H66/G66-1 -> 0.16995798 | I67: =I66/H66-1 -> 0.1674028 | J67: =J66/I66-1 -> 0.13253312 | K67: =K66/J66-1 -> 0.12241184
A69: F. MIX BY GEOGRAPHY (DOMESTIC vs. INTERNATIONAL)
A70: Domestic
A71: Domestic Advances | B71: ='Revenue Model'!B21 -> 2502952 | C71: ='Revenue Model'!C21 -> 2875752 | D71: ='Revenue Model'!D21 -> 3292315 | E71: ='Revenue Model'!E21 -> 3602000 | F71: ='Revenue Model'!F21 -> 4189138 | G71: ='Revenue Model'!G21 -> 4780053.5 | H71: ='Revenue Model'!H21 -> 5424565.2 | I71: ='Revenue Model'!I21 -> 6130750.7 | ... K71: ='Revenue Model'!K21 -> 7769763.8
A72: % of Total Advances | B72: =B71/B28 -> 0.88999988 | C72: =C71/C28 -> 0.88 | D72: =D71/D28 -> 0.87000003 | E72: =E71/E28 -> 0.85335229 | F72: =F71/F28 -> 0.84937916 | G72: =G71/G28 -> 0.84726081 | H72: =H71/H28 -> 0.84553484 | I72: =I71/I28 -> 0.84440188 | ... K72: =K71/K28 -> 0.84458261
A73: Domestic Advances YoY Growth % | B73: n/a | C73: =C71/B71-1 -> 0.14894413 | D73: =D71/C71-1 -> 0.14485359 | E73: =E71/D71-1 -> 0.094062992 | F73: =F71/E71-1 -> 0.16300333 | G73: =G71/F71-1 -> 0.14105898 | H73: =H71/G71-1 -> 0.13483357 | I73: =I71/H71-1 -> 0.13018287 | J73: =J71/I71-1 -> 0.1275167 | K73: =K71/J71-1 -> 0.12401259
A74: Domestic Interest Income | B74: ='Revenue Model'!B23 -> 182715.5 | C74: ='Revenue Model'!C23 -> 218557.15 | D74: ='Revenue Model'!D23 -> 260092.89 | E74: ='Revenue Model'!E23 -> 288160 | F74: ='Revenue Model'!F23 -> 330941.9 | G74: ='Revenue Model'!G23 -> 380014.26 | H74: ='Revenue Model'!H23 -> 433965.22 | I74: ='Revenue Model'!I23 -> 493525.43 | ... K74: ='Revenue Model'!K23 -> 625465.99
A75: International (Foreign Offices)
A76: International Advances | B76: ='Revenue Model'!B26 -> 309354 | C76: ='Revenue Model'!C26 -> 392148 | D76: ='Revenue Model'!D26 -> 491955 | E76: ='Revenue Model'!E26 -> 619000 | F76: ='Revenue Model'!F26 -> 742862 | G76: ='Revenue Model'!G26 -> 861719.92 | H76: ='Revenue Model'!H26 -> 990977.91 | I76: ='Revenue Model'!I26 -> 1129714.8 | ... K76: ='Revenue Model'!K26 -> 1429767.1
A77: % of Total Advances | B77: =B76/B28 -> 0.11000012 | C77: =C76/C28 -> 0.12 | D77: =D76/D28 -> 0.12999997 | E77: =E76/E28 -> 0.14664771 | F77: =F76/F28 -> 0.15062084 | G77: =G76/G28 -> 0.15273919 | H77: =H76/H28 -> 0.15446516 | I77: =I76/I28 -> 0.15559812 | ... K77: =K76/K28 -> 0.15541739
A78: International Advances YoY Growth % | B78: n/a | C78: =C76/B76-1 -> 0.26763514 | D78: =D76/C76-1 -> 0.2545136 | E78: =E76/D76-1 -> 0.25824516 | F78: =F76/E76-1 -> 0.20010016 | G78: =G76/F76-1 -> 0.16 | H78: =H76/G76-1 -> 0.15 | I78: =I76/H76-1 -> 0.14 | J78: =J76/I76-1 -> 0.13 | K78: =K76/J76-1 -> 0.12
A79: International Interest Income | B79: ='Revenue Model'!B27 -> 14848.992 | C79: ='Revenue Model'!C27 -> 19999.548 | D79: ='Revenue Model'!D27 -> 26073.615 | E79: ='Revenue Model'!E27 -> 33426 | F79: ='Revenue Model'!F27 -> 40485.979 | G79: ='Revenue Model'!G27 -> 46963.736 | H79: ='Revenue Model'!H27 -> 54008.296 | I79: ='Revenue Model'!I27 -> 61569.457 | ... K79: ='Revenue Model'!K27 -> 77922.305
A81: TOTAL ADVANCES (tie-out check) | B81: =B71+B76 -> 2812306 | C81: =C71+C76 -> 3267900 | D81: =D71+D76 -> 3784270 | E81: =E71+E76 -> 4221000 | F81: =F71+F76 -> 4932000 | G81: =G71+G76 -> 5641773.5 | H81: =H71+H76 -> 6415543.1 | I81: =I71+I76 -> 7260465.5 | ... K81: =K71+K76 -> 9199530.9

Sheet Income Statement
A1: INCOME STATEMENT
A2: State Bank of India — Standalone P&L, FY22A–FY31E
A3: (₹ crore unless stated) | B3: FY22A | C3: FY23A | D3: FY24A | E3: FY25A | F3: FY26A | G3: FY27E | H3: FY28E | I3: FY29E | J3: FY30E | K3: FY31E
A4: INTEREST INCOME
A5: Interest on Advances | B5: ='Revenue Model'!B31 -> 197564.49 | C5: ='Revenue Model'!C31 -> 238556.7 | D5: ='Revenue Model'!D31 -> 286166.5 | E5: ='Revenue Model'!E31 -> 321586 | F5: ='Revenue Model'!F31 -> 371427.88 | G5: ='Revenue Model'!G31 -> 426977.99 | H5: ='Revenue Model'!H31 -> 487973.51 | I5: ='Revenue Model'!I31 -> 555094.89 | ... K5: ='Revenue Model'!K31 -> 703388.29
A6: Interest on Investments | B6: ='Revenue Model'!B35 -> 95580 | C6: ='Revenue Model'!C35 -> 112299.56 | D6: ='Revenue Model'!D35 -> 118401.85 | E6: ='Revenue Model'!E35 -> 126822 | F6: ='Revenue Model'!F35 -> 122850 | G6: ='Revenue Model'!G35 -> 144406.08 | H6: ='Revenue Model'!H35 -> 162767.89 | I6: ='Revenue Model'!I35 -> 183339.63 | ... K6: ='Revenue Model'!K35 -> 224800.51
A7: Other Interest Income | B7: ='Revenue Model'!B36 -> 4200 | C7: ='Revenue Model'!C36 -> 4500 | D7: ='Revenue Model'!D36 -> 4900 | E7: ='Revenue Model'!E36 -> 5300 | F7: ='Revenue Model'!F36 -> 6100 | G7: ='Revenue Model'!G36 -> 6588 | H7: ='Revenue Model'!H36 -> 7115.04 | I7: ='Revenue Model'!I36 -> 7684.2432 | ... K7: ='Revenue Model'!K36 -> 8962.9013
A8: TOTAL INTEREST INCOME | B8: ='Revenue Model'!B37 -> 297344.49 | C8: ='Revenue Model'!C37 -> 355356.26 | D8: ='Revenue Model'!D37 -> 409468.35 | E8: ='Revenue Model'!E37 -> 453708 | F8: ='Revenue Model'!F37 -> 500377.88 | G8: ='Revenue Model'!G37 -> 577972.07 | H8: ='Revenue Model'!H37 -> 657856.45 | I8: ='Revenue Model'!I37 -> 746118.76 | ... K8: ='Revenue Model'!K37 -> 937151.7
A10: INTEREST EXPENSE
A11: Interest on Deposits | B11: ='Revenue Model'!B47 -> 164064.45 | C11: ='Revenue Model'!C47 -> 195404.79 | D11: ='Revenue Model'!D47 -> 230566.66 | E11: ='Revenue Model'!E47 -> 264854.16 | F11: ='Revenue Model'!F47 -> 300589.7 | G11: ='Revenue Model'!G47 -> 339886.68 | H11: ='Revenue Model'!H47 -> 375272.7 | I11: ='Revenue Model'!I47 -> 412343.23 | ... K11: ='Revenue Model'!K47 -> 508048.1
A12: Interest on Borrowings | B12: ='Revenue Model'!B49 -> 13340 | C12: ='Revenue Model'!C49 -> 15996 | D12: ='Revenue Model'!D49 -> 18850 | E12: ='Revenue Model'!E49 -> 21909 | F12: ='Revenue Model'!F49 -> 25976 | G12: ='Revenue Model'!G49 -> 29093.12 | H12: ='Revenue Model'!H49 -> 32584.294 | I12: ='Revenue Model'!I49 -> 36226.068 | ... K12: ='Revenue Model'!K49 -> 45441.98
A13: TOTAL INTEREST EXPENSE | B13: ='Revenue Model'!B50 -> 177404.45 | C13: ='Revenue Model'!C50 -> 211400.79 | D13: ='Revenue Model'!D50 -> 249416.66 | E13: ='Revenue Model'!E50 -> 286763.16 | F13: ='Revenue Model'!F50 -> 326565.7 | G13: ='Revenue Model'!G50 -> 368979.8 | H13: ='Revenue Model'!H50 -> 407857 | I13: ='Revenue Model'!I50 -> 448569.3 | ... K13: ='Revenue Model'!K50 -> 553490.08
A14: NET INTEREST INCOME (NII) | B14: =B8-B13 -> 119940.04 | C14: =C8-C13 -> 143955.47 | D14: =D8-D13 -> 160051.69 | E14: =E8-E13 -> 166944.85 | F14: =F8-F13 -> 173812.18 | G14: =G8-G13 -> 208992.27 | H14: =H8-H13 -> 249999.45 | I14: =I8-I13 -> 297549.46 | ... K14: =K8-K13 -> 383661.63
A15: NII Growth % YoY | B15: n/a | C15: =C14/B14-1 -> 0.20022865 | D15: =D14/C14-1 -> 0.11181389 | E15: =E14/D14-1 -> 0.043068298 | F15: =F14/E14-1 -> 0.041135343 | G15: =G14/F14-1 -> 0.20240292 | H15: =H14/G14-1 -> 0.19621384 | I15: =I14/H14-1 -> 0.19020048 | J15: =J14/I14-1 -> 0.1424532 | K15: =K14/J14-1 -> 0.12862788
A16: Net Interest Margin % — Domestic (memo) | B16: ='Revenue Model'!B54 -> 0.047919432 | C16: ='Revenue Model'!C54 -> 0.050058374 | D16: ='Revenue Model'!D54 -> 0.048613723 | E16: ='Revenue Model'!E54 -> 0.046347819 | F16: ='Revenue Model'!F54 -> 0.041491156 | G16: ='Revenue Model'!G54 -> 0.043721743 | H16: ='Revenue Model'!H54 -> 0.046086541 | I16: ='Revenue Model'!I54 -> 0.048533936 | ... K16: ='Revenue Model'!K54 -> 0.049378802
A18: NON-INTEREST INCOME
A19: Fee & Commission Income | B19: ='Revenue Model'!B57 -> 24700 | C19: ='Revenue Model'!C57 -> 27900 | D19: ='Revenue Model'!D57 -> 31700 | E19: ='Revenue Model'!E57 -> 35800 | F19: ='Revenue Model'!F57 -> 40400 | G19: ='Revenue Model'!G57 -> 45248 | H19: ='Revenue Model'!H57 -> 50677.76 | I19: ='Revenue Model'!I57 -> 56759.091 | ... K19: ='Revenue Model'!K57 -> 71198.604
A20: Treasury / Trading Gains | B20: ='Revenue Model'!B59 -> 1900 | C20: ='Revenue Model'!C59 -> 6800 | D20: ='Revenue Model'!D59 -> 8200 | E20: ='Revenue Model'!E59 -> 9100 | F20: ='Revenue Model'!F59 -> 14800 | G20: ='Revenue Model'!G59 -> 10360 | H20: ='Revenue Model'!H59 -> 11188.8 | I20: ='Revenue Model'!I59 -> 12083.904 | ... K20: ='Revenue Model'!K59 -> 14094.666
A21: Forex Income | B21: ='Revenue Model'!B60 -> 2400 | C21: ='Revenue Model'!C60 -> 2700 | D21: ='Revenue Model'!D60 -> 3100 | E21: ='Revenue Model'!E60 -> 3600 | F21: ='Revenue Model'!F60 -> 8300 | G21: ='Revenue Model'!G60 -> 5395 | H21: ='Revenue Model'!H60 -> 5826.6 | I21: ='Revenue Model'!I60 -> 6292.728 | ... K21: ='Revenue Model'!K60 -> 7339.8379
A22: Dividend from Subsidiaries | B22: ='Revenue Model'!B61 -> 2100 | C22: ='Revenue Model'!C61 -> 2600 | D22: ='Revenue Model'!D61 -> 3200 | E22: ='Revenue Model'!E61 -> 3900 | F22: ='Revenue Model'!F61 -> 4600 | G22: ='Revenue Model'!G61 -> 5060 | H22: ='Revenue Model'!H61 -> 5566 | I22: ='Revenue Model'!I61 -> 6122.6 | ... K22: ='Revenue Model'!K61 -> 7408.346
A23: Recovery from Written-off Accounts | B23: ='Revenue Model'!B62 -> 7200 | C23: ='Revenue Model'!C62 -> 6500 | D23: ='Revenue Model'!D62 -> 6100 | E23: ='Revenue Model'!E62 -> 5700 | F23: ='Revenue Model'!F62 -> 5200 | G23: ='Revenue Model'!G62 -> 5044 | H23: ='Revenue Model'!H62 -> 4892.68 | I23: ='Revenue Model'!I62 -> 4745.8996 | ... K23: ='Revenue Model'!K62 -> 4465.4169
A24: Other Income | B24: ='Revenue Model'!B63 -> 3500 | C24: ='Revenue Model'!C63 -> 3700 | D24: ='Revenue Model'!D63 -> 4000 | E24: ='Revenue Model'!E63 -> 4300 | F24: ='Revenue Model'!F63 -> 4600 | G24: ='Revenue Model'!G63 -> 4968 | H24: ='Revenue Model'!H63 -> 5365.44 | I24: ='Revenue Model'!I63 -> 5794.6752 | ... K24: ='Revenue Model'!K63 -> 6758.9092
A25: One-off / Exceptional Items (FY26) | B25: ='Revenue Model'!B64 -> 0 | C25: ='Revenue Model'!C64 -> 0 | D25: ='Revenue Model'!D64 -> 0 | E25: ='Revenue Model'!E64 -> 0 | F25: ='Revenue Model'!F64 -> 4618 | G25: ='Revenue Model'!G64 -> 0 | H25: ='Revenue Model'!H64 -> 0 | I25: ='Revenue Model'!I64 -> 0 | ... K25: ='Revenue Model'!K64 -> 0
A26: TOTAL NON-INTEREST INCOME | B26: ='Revenue Model'!B65 -> 41800 | C26: ='Revenue Model'!C65 -> 50200 | D26: ='Revenue Model'!D65 -> 56300 | E26: ='Revenue Model'!E65 -> 62400 | F26: ='Revenue Model'!F65 -> 82518 | G26: ='Revenue Model'!G65 -> 76075 | H26: ='Revenue Model'!H65 -> 83517.28 | I26: ='Revenue Model'!I65 -> 91798.898 | ... K26: ='Revenue Model'!K65 -> 111265.78
A27: TOTAL NET REVENUE | B27: =B14+B26 -> 161740.04 | C27: =C14+C26 -> 194155.47 | D27: =D14+D26 -> 216351.69 | E27: =E14+E26 -> 229344.85 | F27: =F14+F26 -> 256330.18 | G27: =G14+G26 -> 285067.27 | H27: =H14+H26 -> 333516.73 | I27: =I14+I26 -> 389348.36 | ... K27: =K14+K26 -> 494927.41
A28: Total Net Revenue Growth % YoY | B28: n/a | C28: =C27/B27-1 -> 0.20041687 | D28: =D27/C27-1 -> 0.11432189 | E28: =E27/D27-1 -> 0.060055708 | F28: =F27/E27-1 -> 0.1176627 | G28: =G27/F27-1 -> 0.11210967 | H28: =H27/G27-1 -> 0.16995798 | I28: =I27/H27-1 -> 0.1674028 | J28: =J27/I27-1 -> 0.13253312 | K28: =K27/J27-1 -> 0.12241184
A30: OPERATING EXPENSES
A31: Employee Cost | B31: 58500 | C31: 62700 | D31: 78200 | E31: 72300 | F31: 79600 | G31: =F31*(1+Assumptions!G29) -> 85968 | H31: =G31*(1+Assumptions!H29) -> 92845.44 | I31: =H31*(1+Assumptions!I29) -> 100273.08 | J31: =I31*(1+Assumptions!J29) -> 108294.92 | K31: =J31*(1+Assumptions!K29) -> 116958.51
A32: Rent, Taxes & Lighting | B32: 5200 | C32: 5700 | D32: 6300 | E32: 7000 | F32: 7700 | G32: =F32*(1+Assumptions!G30) -> 8547 | H32: =G32*(1+Assumptions!H30) -> 9487.17 | I32: =H32*(1+Assumptions!I30) -> 10530.759 | J32: =I32*(1+Assumptions!J30) -> 11583.835 | K32: =J32*(1+Assumptions!K30) -> 12742.218
A33: Depreciation | B33: 3600 | C33: 3900 | D33: 4300 | E33: 4700 | F33: 5100 | G33: =F33*(1+Assumptions!G30) -> 5661 | H33: =G33*(1+Assumptions!H30) -> 6283.71 | I33: =H33*(1+Assumptions!I30) -> 6974.9181 | J33: =I33*(1+Assumptions!J30) -> 7672.4099 | K33: =J33*(1+Assumptions!K30) -> 8439.6509
A34: Printing, Stationery & Admin Expenses | B34: 7800 | C34: 8300 | D34: 9100 | E34: 9900 | F34: 10700 | G34: =F34*(1+Assumptions!G30) -> 11877 | H34: =G34*(1+Assumptions!H30) -> 13183.47 | I34: =H34*(1+Assumptions!I30) -> 14633.652 | J34: =I34*(1+Assumptions!J30) -> 16097.017 | K34: =J34*(1+Assumptions!K30) -> 17706.719
A35: Other Operating Expenses (incl. technology) | B35: 16018 | C35: 30655 | D35: 20946 | E35: 26813 | F35: 31223 | G35: =F35*(1+Assumptions!G30) -> 34657.53 | H35: =G35*(1+Assumptions!H30) -> 38469.858 | I35: =H35*(1+Assumptions!I30) -> 42701.543 | J35: =I35*(1+Assumptions!J30) -> 46971.697 | K35: =J35*(1+Assumptions!K30) -> 51668.867
A36: TOTAL OPERATING EXPENSES | B36: =B31+B32+B33+B34+B35 -> 91118 | C36: =C31+C32+C33+C34+C35 -> 111255 | D36: =D31+D32+D33+D34+D35 -> 118846 | E36: =E31+E32+E33+E34+E35 -> 120713 | F36: =F31+F32+F33+F34+F35 -> 134323 | G36: =G31+G32+G33+G34+G35 -> 146710.53 | H36: =H31+H32+H33+H34+H35 -> 160269.65 | I36: =I31+I32+I33+I34+I35 -> 175113.95 | ... K36: =K31+K32+K33+K34+K35 -> 207515.97
A37: Cost-to-Income Ratio % | B37: =B36/B27 -> 0.56336082 | C37: =C36/C27 -> 0.57302017 | D37: =D36/D27 -> 0.54931856 | E37: =E36/E27 -> 0.52633841 | F37: =F36/F27 -> 0.52402335 | G37: =G36/G27 -> 0.51465231 | H37: =H36/H27 -> 0.48054456 | I37: =I36/I27 -> 0.44976161 | ... K37: =K36/K27 -> 0.41928567
A38: OPERATING PROFIT (Pre-Provision Operating Profit) | B38: =B27-B36 -> 70622.038 | C38: =C27-C36 -> 82900.47 | D38: =D27-D36 -> 97505.691 | E38: =E27-E36 -> 108631.85 | F38: =F27-F36 -> 122007.18 | G38: =G27-G36 -> 138356.74 | H38: =H27-H36 -> 173247.08 | I38: =I27-I36 -> 214234.42 | ... K38: =K27-K36 -> 287411.44
A39: PPOP Margin % (of Total Net Revenue) | B39: =B38/B27 -> 0.43663918 | C39: =C38/C27 -> 0.42697983 | D39: =D38/D27 -> 0.45068144 | E39: =E38/E27 -> 0.47366159 | F39: =F38/F27 -> 0.47597665 | G39: =G38/G27 -> 0.48534769 | H39: =H38/H27 -> 0.51945544 | I39: =I38/I27 -> 0.55023839 | ... K39: =K38/K27 -> 0.58071433
A41: PROVISIONS & CONTINGENCIES
A42: Loan Loss Provisions (Credit Cost) | B42: 19200 | C42: 15100 | D42: 12200 | E42: 10800 | F42: 11200 | G42: ='Revenue Model'!G28*Assumptions!G33 -> 23695.448 | H42: ='Revenue Model'!H28*Assumptions!H33 -> 26945.281 | I42: ='Revenue Model'!I28*Assumptions!I33 -> 32672.095 | J42: ='Revenue Model'!J28*Assumptions!J33 -> 36850.957 | K42: ='Revenue Model'!K28*Assumptions!K33 -> 41397.889
A43: Provision for Standard Assets | B43: 1400 | C43: 1100 | D43: 900 | E43: 700 | F43: 800 | G43: =F43*(1+Assumptions!G30) -> 888 | H43: =G43*(1+Assumptions!H30) -> 985.68 | I43: =H43*(1+Assumptions!I30) -> 1094.1048 | J43: =I43*(1+Assumptions!J30) -> 1203.5153 | K43: =J43*(1+Assumptions!K30) -> 1323.8668
A44: Provision for Investments (Depreciation) | B44: 2600 | C44: -1800 | D44: 1200 | E44: 600 | F44: 900 | G44: =F44*1.05 -> 945 | H44: =G44*1.05 -> 992.25 | I44: =H44*1.05 -> 1041.8625 | J44: =I44*1.05 -> 1093.9556 | K44: =J44*1.05 -> 1148.6534
A45: Other Provisions | B45: 900 | C45: 1300 | D45: 1500 | E45: 1800 | F45: 2100 | G45: =F45*(1+Assumptions!G30) -> 2331 | H45: =G45*(1+Assumptions!H30) -> 2587.41 | I45: =H45*(1+Assumptions!I30) -> 2872.0251 | J45: =I45*(1+Assumptions!J30) -> 3159.2276 | K45: =J45*(1+Assumptions!K30) -> 3475.1504
A46: TOTAL PROVISIONS | B46: =B42+B43+B44+B45 -> 24100 | C46: =C42+C43+C44+C45 -> 15700 | D46: =D42+D43+D44+D45 -> 15800 | E46: =E42+E43+E44+E45 -> 13900 | F46: =F42+F43+F44+F45 -> 15000 | G46: =G42+G43+G44+G45 -> 27859.448 | H46: =H42+H43+H44+H45 -> 31510.621 | I46: =I42+I43+I44+I45 -> 37680.087 | ... K46: =K42+K43+K44+K45 -> 47345.56
A47: Credit Cost % (Loan Loss Provisions / Gross Advances, memo) | B47: =B42/'Revenue Model'!B28 -> 0.0068271376 | C47: =C42/'Revenue Model'!C28 -> 0.0046207044 | D47: =D42/'Revenue Model'!D28 -> 0.0032238714 | E47: =E42/'Revenue Model'!E28 -> 0.0025586354 | F47: =F42/'Revenue Model'!F28 -> 0.002270884 | G47: =G42/'Revenue Model'!G28 -> 0.0042 | H47: =H42/'Revenue Model'!H28 -> 0.0042 | I47: =I42/'Revenue Model'!I28 -> 0.0045 | ... K47: =K42/'Revenue Model'!K28 -> 0.0045
A48: PROFIT BEFORE TAX (PBT) | B48: =B38-B46 -> 46522.038 | C48: =C38-C46 -> 67200.47 | D48: =D38-D46 -> 81705.691 | E48: =E38-E46 -> 94731.845 | F48: =F38-F46 -> 107007.18 | G48: =G38-G46 -> 110497.29 | H48: =H38-H46 -> 141736.46 | I48: =I38-I46 -> 176554.33 | ... K48: =K38-K46 -> 240065.88
A49: Tax Expense | B49: =B48*Assumptions!B40 -> 14887.052 | C49: =C48*Assumptions!C40 -> 17001.719 | D49: =D48*Assumptions!D40 -> 20589.834 | E49: =E48*Assumptions!E40 -> 23872.425 | F49: =F48*Assumptions!F40 -> 26965.809 | G49: =G48*Assumptions!G40 -> 27845.318 | H49: =H48*Assumptions!H40 -> 35717.588 | I49: =I48*Assumptions!I40 -> 44491.691 | ... K49: =K48*Assumptions!K40 -> 60496.601
A50: Effective Tax Rate % | B50: =Assumptions!B40 -> 0.32 | C50: =Assumptions!C40 -> 0.253 | D50: =Assumptions!D40 -> 0.252 | E50: =Assumptions!E40 -> 0.252 | F50: =Assumptions!F40 -> 0.252 | G50: =Assumptions!G40 -> 0.252 | H50: =Assumptions!H40 -> 0.252 | I50: =Assumptions!I40 -> 0.252 | ... K50: =Assumptions!K40 -> 0.252
A51: NET PROFIT (PAT) | B51: =B48-B49 -> 31634.986 | C51: =C48-C49 -> 50198.751 | D51: =D48-D49 -> 61115.857 | E51: =E48-E49 -> 70859.42 | F51: =F48-F49 -> 80041.37 | G51: =G48-G49 -> 82651.975 | H51: =H48-H49 -> 106018.87 | I51: =I48-I49 -> 132062.64 | ... K51: =K48-K49 -> 179569.28
A52: Net Profit Growth % YoY | B52: n/a | C52: =C51/B51-1 -> 0.58681124 | D52: =D51/C51-1 -> 0.21747764 | E52: =E51/D51-1 -> 0.15942774 | F52: =F51/E51-1 -> 0.1295798 | G52: =G51/F51-1 -> 0.032615702 | H52: =H51/G51-1 -> 0.28271431 | I52: =I51/H51-1 -> 0.24565217 | J52: =J51/I51-1 -> 0.17823438 | K52: =K51/J51-1 -> 0.15403871
A53: Net Margin % (PAT / Total Net Revenue) | B53: =B51/B27 -> 0.19559156 | C53: =C51/C27 -> 0.25854925 | D53: =D51/D27 -> 0.28248384 | E53: =E51/E27 -> 0.30896452 | F53: =F51/F27 -> 0.31225886 | G53: =G51/G27 -> 0.28993849 | H53: =H51/H27 -> 0.31788172 | I53: =I51/I27 -> 0.33918889 | ... K53: =K51/K27 -> 0.36281942
A55: PER SHARE DATA & KEY RATIOS
A56: Basic Shares Outstanding (crore) | B56: 892.46 | C56: 892.46 | D56: 892.46 | E56: 892.46 | F56: 909.2 | G56: =F56*(1+Assumptions!G42) -> 909.2 | H56: =G56*(1+Assumptions!H42) -> 909.2 | I56: =H56*(1+Assumptions!I42) -> 909.2 | J56: =I56*(1+Assumptions!J42) -> 909.2 | K56: =J56*(1+Assumptions!K42) -> 909.2
A57: Diluted Shares Outstanding (crore) | B57: =B56*1.001 -> 893.35246 | C57: =C56*1.001 -> 893.35246 | D57: =D56*1.001 -> 893.35246 | E57: =E56*1.001 -> 893.35246 | F57: =F56*1.001 -> 910.1092 | G57: =G56*1.001 -> 910.1092 | H57: =H56*1.001 -> 910.1092 | I57: =I56*1.001 -> 910.1092 | ... K57: =K56*1.001 -> 910.1092
A58: Basic EPS (₹) | B58: =B51/B56 -> 35.446951 | C58: =C51/C56 -> 56.24762 | D58: =D51/D56 -> 68.48022 | E58: =E51/E56 -> 79.397867 | F58: =F51/F56 -> 88.034942 | G58: =G51/G56 -> 90.906264 | H58: =H51/H56 -> 116.60677 | I58: =I51/I56 -> 145.25147 | ... K58: =K51/K56 -> 197.5025
A59: Diluted EPS (₹) | B59: =B51/B57 -> 35.411539 | C59: =C51/C57 -> 56.191429 | D59: =D51/D57 -> 68.411808 | E59: =E51/E57 -> 79.318548 | F59: =F51/F57 -> 87.946995 | G59: =G51/G57 -> 90.815448 | H59: =H51/H57 -> 116.49027 | I59: =I51/I57 -> 145.10636 | ... K59: =K51/K57 -> 197.3052
A60: Dividend Per Share (₹) | B60: 7.1 | C60: 11.3 | D60: 13.7 | E60: 15.9 | F60: 17.35 | G60: =G58*Assumptions!G41 -> 19.544847 | H60: =H58*Assumptions!H41 -> 25.070455 | I60: =I58*Assumptions!I41 -> 31.229066 | J60: =J58*Assumptions!J41 -> 36.79516 | K60: =K58*Assumptions!K41 -> 42.463038
A61: Dividend Payout Ratio % | B61: =B60*B56/B51 -> 0.20029932 | C61: =C60*C56/C51 -> 0.20089739 | D61: =D60*D56/D51 -> 0.20005777 | E61: =E60*E56/E51 -> 0.20025727 | F61: =F60*F56/F51 -> 0.19708084 | G61: =G60*G56/G51 -> 0.215 | H61: =H60*H56/H51 -> 0.215 | I61: =I60*I56/I51 -> 0.215 | ... K61: =K60*K56/K51 -> 0.215
A62: Return on Assets (ROA) % | B62: 0.0067 | C62: 0.0096 | D62: 0.0104 | E62: 0.011 | F62: 0.0112 | G62: =G51/AVERAGE('Balance Sheet'!F46,'Balance Sheet'!G46) -> 0.01075306 | H62: =H51/AVERAGE('Balance Sheet'!G46,'Balance Sheet'!H46) -> 0.012333789 | I62: =I51/AVERAGE('Balance Sheet'!H46,'Balance Sheet'!I46) -> 0.013748612 | J62: =J51/AVERAGE('Balance Sheet'!I46,'Balance Sheet'!J46) -> 0.014516281 | K62: =K51/AVERAGE('Balance Sheet'!J46,'Balance Sheet'!K46) -> 0.015035504
A63: Return on Equity (ROE) % | B63: 0.139 | C63: 0.169 | D63: 0.2032 | E63: 0.1987 | F63: 0.1857 | G63: =G51/AVERAGE('Balance Sheet'!F8,'Balance Sheet'!G8) -> 0.16688665 | H63: =H51/AVERAGE('Balance Sheet'!G8,'Balance Sheet'!H8) -> 0.18622522 | I63: =I51/AVERAGE('Balance Sheet'!H8,'Balance Sheet'!I8) -> 0.19926417 | J63: =J51/AVERAGE('Balance Sheet'!I8,'Balance Sheet'!J8) -> 0.20060446 | K63: =K51/AVERAGE('Balance Sheet'!J8,'Balance Sheet'!K8) -> 0.19793493
A64: Book Value per Share (₹) (memo, linked from Balance Sheet) | B64: ='Balance Sheet'!B9 -> 255.34478 | C64: ='Balance Sheet'!C9 -> 300.2924 | D64: ='Balance Sheet'!D9 -> 355.07262 | E64: ='Balance Sheet'!E9 -> 418.57048 | F64: ='Balance Sheet'!F9 -> 509.04549 | G64: ='Balance Sheet'!G9 -> 580.39173 | H64: ='Balance Sheet'!H9 -> 671.92804 | I64: ='Balance Sheet'!I9 -> 785.95045 | ... K64: ='Balance Sheet'!K9 -> 1075.335

Sheet Balance Sheet
A1: BALANCE SHEET
A2: State Bank of India — Standalone statement of assets & liabilities, FY22A–FY31E
A3: (₹ crore unless stated) | B3: FY22A | C3: FY23A | D3: FY24A | E3: FY25A | F3: FY26A | G3: FY27E | H3: FY28E | I3: FY29E | J3: FY30E | K3: FY31E
A4: LIABILITIES
A5: Shareholders' Equity
A6: Equity Share Capital | B6: 892 | C6: 892 | D6: 892 | E6: 892 | F6: 923 | G6: ='Income Statement'!G56 -> 909.2 | H6: ='Income Statement'!H56 -> 909.2 | I6: ='Income Statement'!I56 -> 909.2 | J6: ='Income Statement'!J56 -> 909.2 | K6: ='Income Statement'!K56 -> 909.2
A7: Reserves & Surplus | B7: 226993 | C7: =B7+'Income Statement'!C51-'Income Statement'!C60*'Income Statement'!C56 -> 267106.95 | D7: =C7+'Income Statement'!D51-'Income Statement'!D60*'Income Statement'!D56 -> 315996.11 | E7: =D7+'Income Statement'!E51-'Income Statement'!E60*'Income Statement'!E56 -> 372665.41 | F7: =E7+'Income Statement'!F51-'Income Statement'!F60*'Income Statement'!F56+24969 -> 461901.16 | G7: =F7+'Income Statement'!G51-'Income Statement'!G60*'Income Statement'!G56 -> 526782.96 | H7: =G7+'Income Statement'!H51-'Income Statement'!H60*'Income Statement'!H56 -> 610007.78 | I7: =H7+'Income Statement'!I51-'Income Statement'!I60*'Income Statement'!I56 -> 713676.95 | J7: =I7+'Income Statement'!J51-'Income Statement'!J60*'Income Statement'!J56 -> 835823.53 | K7: =J7+'Income Statement'!K51-'Income Statement'!K60*'Income Statement'!K56 -> 976785.41
A8: TOTAL SHAREHOLDERS' EQUITY | B8: =B6+B7 -> 227885 | C8: =C6+C7 -> 267998.95 | D8: =D6+D7 -> 316888.11 | E8: =E6+E7 -> 373557.41 | F8: =F6+F7 -> 462824.16 | G8: =G6+G7 -> 527692.16 | H8: =H6+H7 -> 610916.98 | I8: =I6+I7 -> 714586.15 | ... K8: =K6+K7 -> 977694.61
A9: Book Value per Share (₹) (memo) | B9: =B8/'Income Statement'!B56 -> 255.34478 | C9: =C8/'Income Statement'!C56 -> 300.2924 | D9: =D8/'Income Statement'!D56 -> 355.07262 | E9: =E8/'Income Statement'!E56 -> 418.57048 | F9: =F8/'Income Statement'!F56 -> 509.04549 | G9: =G8/'Income Statement'!G56 -> 580.39173 | H9: =H8/'Income Statement'!H56 -> 671.92804 | I9: =I8/'Income Statement'!I56 -> 785.95045 | ... K9: =K8/'Income Statement'!K56 -> 1075.335
A11: Deposits
A12: Current Account Deposits | B12: 312215 | C12: 323612 | D12: 344479 | E12: 365701 | F12: 400815 | G12: ='Revenue Model'!G42*0.17 -> 443679.6 | H12: ='Revenue Model'!H42*0.17 -> 490897.35 | I12: ='Revenue Model'!I42*0.17 -> 544521.86 | J12: ='Revenue Model'!J42*0.17 -> 604419.26 | K12: ='Revenue Model'!K42*0.17 -> 670905.38
A13: Savings Account Deposits | B13: 1524345 | C13: 1579986 | D13: 1681869 | E13: 1785484 | F13: 1956920 | G13: ='Revenue Model'!G42*0.83 -> 2166200.4 | H13: ='Revenue Model'!H42*0.83 -> 2396734.1 | I13: ='Revenue Model'!I42*0.83 -> 2658547.9 | J13: ='Revenue Model'!J42*0.83 -> 2950988.2 | K13: ='Revenue Model'!K42*0.83 -> 3275596.9
A14: Term Deposits | B14: ='Revenue Model'!B43 -> 2214974 | C14: ='Revenue Model'!C43 -> 2564942 | D14: ='Revenue Model'!D43 -> 2940192 | E14: ='Revenue Model'!E43 -> 3230815 | F14: ='Revenue Model'!F43 -> 3617265 | G14: ='Revenue Model'!G43 -> 4082120 | H14: ='Revenue Model'!H43 -> 4573948.5 | I14: ='Revenue Model'!I43 -> 5116591.9 | ... K14: ='Revenue Model'!K43 -> 6304152.9
A15: TOTAL DEPOSITS | B15: =B12+B13+B14 -> 4051534 | C15: =C12+C13+C14 -> 4468540 | D15: =D12+D13+D14 -> 4966540 | E15: =E12+E13+E14 -> 5382000 | F15: =F12+F13+F14 -> 5975000 | G15: =G12+G13+G14 -> 6692000 | H15: =H12+H13+H14 -> 7461580 | I15: =I12+I13+I14 -> 8319661.7 | ... K15: =K12+K13+K14 -> 10250655
A16: CASA Ratio % (memo) | B16: =(B12+B13)/B15 -> 0.45329991 | C16: =(C12+C13)/C15 -> 0.42599999 | D16: =(D12+D13)/D15 -> 0.40799994 | E16: =(E12+E13)/E15 -> 0.39969993 | F16: =(F12+F13)/F15 -> 0.3946 | G16: =(G12+G13)/G15 -> 0.39 | H16: =(H12+H13)/H15 -> 0.387 | I16: =(I12+I13)/I15 -> 0.385 | ... K16: =(K12+K13)/K15 -> 0.385
A17: Deposits YoY Growth % | B17: n/a | C17: =C15/B15-1 -> 0.10292546 | D17: =D15/C15-1 -> 0.1114458 | E17: =E15/D15-1 -> 0.083651798 | F17: =F15/E15-1 -> 0.11018209 | G17: =G15/F15-1 -> 0.12 | H17: =H15/G15-1 -> 0.115 | I17: =I15/H15-1 -> 0.115 | J17: =J15/I15-1 -> 0.11 | K17: =K15/J15-1 -> 0.11
A19: Borrowings
A20: Domestic Borrowings | B20: 148000 | C20: 162000 | D20: 178000 | E20: 196000 | F20: 224000 | G20: =F20*1.11 -> 248640 | H20: =G20*1.11 -> 275990.4 | I20: =H20*1.11 -> 306349.34 | J20: =I20*1.11 -> 340047.77 | K20: =J20*1.11 -> 377453.03
A21: Foreign Currency Borrowings / AT1 & Tier-2 Bonds | B21: 82000 | C21: 96000 | D21: 112000 | E21: 131000 | F21: 158000 | G21: =F21*1.15 -> 181700 | H21: =G21*1.15 -> 208955 | I21: =H21*1.15 -> 240298.25 | J21: =I21*1.15 -> 276342.99 | K21: =J21*1.15 -> 317794.44
A22: TOTAL BORROWINGS | B22: =B20+B21 -> 230000 | C22: =C20+C21 -> 258000 | D22: =D20+D21 -> 290000 | E22: =E20+E21 -> 327000 | F22: =F20+F21 -> 382000 | G22: =G20+G21 -> 430340 | H22: =H20+H21 -> 484945.4 | I22: =I20+I21 -> 546647.59 | ... K22: =K20+K21 -> 695247.46
A24: Other Liabilities & Provisions | B24: 312000 | C24: 338000 | D24: 368000 | E24: 398000 | F24: 432000 | G24: =F24*1.09 -> 470880 | H24: =G24*1.09 -> 513259.2 | I24: =H24*1.09 -> 559452.53 | J24: =I24*1.09 -> 609803.26 | K24: =J24*1.09 -> 664685.55
A25: TOTAL LIABILITIES | B25: =B8+B15+B22+B24 -> 4821419 | C25: =C8+C15+C22+C24 -> 5332539 | D25: =D8+D15+D22+D24 -> 5941428.1 | E25: =E8+E15+E22+E24 -> 6480557.4 | F25: =F8+F15+F22+F24 -> 7251824.2 | G25: =G8+G15+G22+G24 -> 8120912.2 | H25: =H8+H15+H22+H24 -> 9070701.6 | I25: =I8+I15+I22+I24 -> 10140348 | ... K25: =K8+K15+K22+K24 -> 12588283
A28: ASSETS
A29: Cash & Balances with RBI | B29: 195000 | C29: 210000 | D29: 235000 | E29: 258000 | F29: 288000 | G29: =G15*0.045 -> 301140 | H29: =H15*0.045 -> 335771.1 | I29: =I15*0.045 -> 374384.78 | J29: =J15*0.045 -> 415567.1 | K29: =K15*0.045 -> 461279.48
A30: Balances with Banks & Money at Call | B30: 98000 | C30: 105000 | D30: 118000 | E30: 129000 | F30: 142000 | G30: =F30*1.09 -> 154780 | H30: =G30*1.09 -> 168710.2 | I30: =H30*1.09 -> 183894.12 | J30: =I30*1.09 -> 200444.59 | K30: =J30*1.09 -> 218484.6
A31: Investments
A32: Government Securities (SLR) | B32: 1263600 | C32: 1492226 | D32: 1646229 | E32: 1720368 | F32: 1825200 | G32: ='Revenue Model'!G34*0.78 -> 2011370.4 | H32: ='Revenue Model'!H34*0.78 -> 2207981.9 | I32: ='Revenue Model'!I34*0.78 -> 2423812.1 | J32: ='Revenue Model'!J34*0.78 -> 2650438.5 | K32: ='Revenue Model'!K34*0.78 -> 2898254.5
A33: Other Investments (Non-SLR) | B33: 356400 | C33: 420884 | D33: 464321 | E33: 485232 | F33: 514800 | G33: ='Revenue Model'!G34*0.22 -> 567309.6 | H33: ='Revenue Model'!H34*0.22 -> 622764.11 | I33: ='Revenue Model'!I34*0.22 -> 683639.31 | J33: ='Revenue Model'!J34*0.22 -> 747559.58 | K33: ='Revenue Model'!K34*0.22 -> 817456.4
A34: TOTAL INVESTMENTS | B34: =B32+B33 -> 1620000 | C34: =C32+C33 -> 1913110 | D34: =D32+D33 -> 2110550 | E34: =E32+E33 -> 2205600 | F34: =F32+F33 -> 2340000 | G34: =G32+G33 -> 2578680 | H34: =H32+H33 -> 2830746 | I34: =I32+I33 -> 3107451.4 | ... K34: =K32+K33 -> 3715710.9
A35: Advances
A36: Gross Advances | B36: ='Revenue Model'!B28 -> 2812306 | C36: ='Revenue Model'!C28 -> 3267900 | D36: ='Revenue Model'!D28 -> 3784270 | E36: ='Revenue Model'!E28 -> 4221000 | F36: ='Revenue Model'!F28 -> 4932000 | G36: ='Revenue Model'!G28 -> 5641773.5 | H36: ='Revenue Model'!H28 -> 6415543.1 | I36: ='Revenue Model'!I28 -> 7260465.5 | ... K36: ='Revenue Model'!K28 -> 9199530.9
A37: Gross NPA (₹ cr) | B37: =B36*Assumptions!B34 -> 111648.55 | C37: =C36*Assumptions!C34 -> 90847.62 | D37: =D36*Assumptions!D34 -> 84767.648 | E37: =E36*Assumptions!E34 -> 76822.2 | F37: =F36*Assumptions!F34 -> 73486.8 | G37: =G36*Assumptions!G34 -> 81805.715 | H37: =H36*Assumptions!H34 -> 91100.712 | I37: =I36*Assumptions!I34 -> 101646.52 | ... K37: =K36*Assumptions!K34 -> 128793.43
A38: Less: Cumulative Provision for NPA | B38: =B37*Assumptions!B36 -> 84071.357 | C38: =C37*Assumptions!C36 -> 69770.972 | D38: =D37*Assumptions!D36 -> 63999.574 | E38: =E37*Assumptions!E36 -> 57171.081 | F38: =F37*Assumptions!F36 -> 54644.784 | G38: =G37*Assumptions!G36 -> 60945.258 | H38: =H37*Assumptions!H36 -> 67870.031 | I38: =I37*Assumptions!I36 -> 75726.655 | ... K38: =K37*Assumptions!K36 -> 95951.107
A39: NET ADVANCES | B39: =B36-B38 -> 2728234.6 | C39: =C36-C38 -> 3198129 | D39: =D36-D38 -> 3720270.4 | E39: =E36-E38 -> 4163828.9 | F39: =F36-F38 -> 4877355.2 | G39: =G36-G38 -> 5580828.2 | H39: =H36-H38 -> 6347673.1 | I39: =I36-I38 -> 7184738.9 | ... K39: =K36-K38 -> 9103579.8
A40: Gross NPA Ratio % (memo) | B40: =Assumptions!B34 -> 0.0397 | C40: =Assumptions!C34 -> 0.0278 | D40: =Assumptions!D34 -> 0.0224 | E40: =Assumptions!E34 -> 0.0182 | F40: =Assumptions!F34 -> 0.0149 | G40: =Assumptions!G34 -> 0.0145 | H40: =Assumptions!H34 -> 0.0142 | I40: =Assumptions!I34 -> 0.014 | ... K40: =Assumptions!K34 -> 0.014
A41: Net NPA Ratio % (memo) | B41: =Assumptions!B35 -> 0.0102 | C41: =Assumptions!C35 -> 0.0067 | D41: =Assumptions!D35 -> 0.0057 | E41: =Assumptions!E35 -> 0.0047 | F41: =Assumptions!F35 -> 0.0039 | G41: =Assumptions!G35 -> 0.0038 | H41: =Assumptions!H35 -> 0.0037 | I41: =Assumptions!I35 -> 0.0036 | ... K41: =Assumptions!K35 -> 0.0036
A42: Provision Coverage Ratio % (memo) | B42: =Assumptions!B36 -> 0.753 | C42: =Assumptions!C36 -> 0.768 | D42: =Assumptions!D36 -> 0.755 | E42: =Assumptions!E36 -> 0.7442 | F42: =Assumptions!F36 -> 0.7436 | G42: =Assumptions!G36 -> 0.745 | H42: =Assumptions!H36 -> 0.745 | I42: =Assumptions!I36 -> 0.745 | ... K42: =Assumptions!K36 -> 0.745
A44: Fixed Assets (Net) | B44: 42000 | C44: 43500 | D44: 45200 | E44: 47000 | F44: 49200 | G44: =F44*1.05 -> 51660 | H44: =G44*1.05 -> 54243 | I44: =H44*1.05 -> 56955.15 | J44: =I44*1.05 -> 59802.908 | K44: =J44*1.05 -> 62793.053
A45: Other Assets (balancing item — see Notes) | B45: =B25-(B29+B30+B34+B39+B44) -> 138184.36 | C45: =C25-(C29+C30+C34+C39+C44) -> -137200.07 | D45: =D25-(D29+D30+D34+D39+D44) -> -287592.32 | E45: =E25-(E29+E30+E34+E39+E44) -> -322871.5 | F45: =F25-(F29+F30+F34+F39+F44) -> -444731.05 | G45: =G25-(G29+G30+G34+G39+G44) -> -546176.03 | H45: =H25-(H29+H30+H34+H39+H44) -> -666441.79 | I45: =I25-(I29+I30+I34+I39+I44) -> -767076.34 | ... K45: =K25-(K29+K30+K34+K39+K44) -> -973565.04
A46: TOTAL ASSETS | B46: =B29+B30+B34+B39+B44+B45 -> 4821419 | C46: =C29+C30+C34+C39+C44+C45 -> 5332539 | D46: =D29+D30+D34+D39+D44+D45 -> 5941428.1 | E46: =E29+E30+E34+E39+E44+E45 -> 6480557.4 | F46: =F29+F30+F34+F39+F44+F45 -> 7251824.2 | G46: =G29+G30+G34+G39+G44+G45 -> 8120912.2 | H46: =H29+H30+H34+H39+H44+H45 -> 9070701.6 | I46: =I29+I30+I34+I39+I44+I45 -> 10140348 | ... K46: =K29+K30+K34+K39+K44+K45 -> 12588283
A49: BALANCE CHECK (Total Assets − Total Liabilities; must equal zero) | B49: =B46-B25 -> 0 | C49: =C46-C25 -> 0 | D49: =D46-D25 -> 0 | E49: =E46-E25 -> 0 | F49: =F46-F25 -> 0 | G49: =G46-G25 -> 0 | H49: =H46-H25 -> 0 | I49: =I46-I25 -> 0 | ... K49: =K46-K25 -> 0
A51: CAPITAL ADEQUACY (MEMO)
A52: Risk-Weighted Assets (RWA) | B52: =B36*0.62 -> 1743629.7 | C52: =C36*0.62 -> 2026098 | D52: =D36*0.62 -> 2346247.4 | E52: =E36*0.62 -> 2617020 | F52: =F36*0.62 -> 3057840 | G52: =G36*0.62 -> 3497899.5 | H52: =H36*0.62 -> 3977636.7 | I52: =I36*0.62 -> 4501488.6 | ... K52: =K36*0.62 -> 5703709.2
A53: CET1 Ratio % | B53: 0.0971 | C53: 0.1013 | D53: 0.1036 | E53: 0.1081 | F53: 0.114 | G53: =G8/G52 -> 0.15085973 | H53: =H8/H52 -> 0.15358793 | I53: =I8/I52 -> 0.15874441 | J53: =J8/J52 -> 0.16480061 | K53: =K8/K52 -> 0.17141383
A54: Tier 1 Capital Ratio % | B54: 0.112 | C54: 0.1198 | D54: 0.121 | E54: 0.126 | F54: 0.135 | G54: =F54 -> 0.135 | H54: =G54 -> 0.135 | I54: =H54 -> 0.135 | J54: =I54 -> 0.135 | K54: =J54 -> 0.135
A55: Total Capital Adequacy Ratio (CAR) % (guided, Assumptions) | B55: =Assumptions!B37 -> 0.1383 | C55: =Assumptions!C37 -> 0.1468 | D55: =Assumptions!D37 -> 0.1428 | E55: =Assumptions!E37 -> 0.1425 | F55: =Assumptions!F37 -> 0.154 | G55: =Assumptions!G37 -> 0.152 | H55: =Assumptions!H37 -> 0.153 | I55: =Assumptions!I37 -> 0.154 | ... K55: =Assumptions!K37 -> 0.155

Sheet Cash Flow Statement
A1: CASH FLOW STATEMENT
A2: State Bank of India — Indirect method, adapted for a bank's balance-sheet structure
A3: (₹ crore unless stated) | B3: FY22A | C3: FY23A | D3: FY24A | E3: FY25A | F3: FY26A | G3: FY27E | H3: FY28E | I3: FY29E | J3: FY30E | K3: FY31E
A4: CASH FLOW FROM OPERATING ACTIVITIES
A5: Net Profit Before Tax | B5: ='Income Statement'!B48 -> 46522.038 | C5: ='Income Statement'!C48 -> 67200.47 | D5: ='Income Statement'!D48 -> 81705.691 | E5: ='Income Statement'!E48 -> 94731.845 | F5: ='Income Statement'!F48 -> 107007.18 | G5: ='Income Statement'!G48 -> 110497.29 | H5: ='Income Statement'!H48 -> 141736.46 | I5: ='Income Statement'!I48 -> 176554.33 | ... K5: ='Income Statement'!K48 -> 240065.88
A6: Add: Depreciation | B6: ='Income Statement'!B33 -> 3600 | C6: ='Income Statement'!C33 -> 3900 | D6: ='Income Statement'!D33 -> 4300 | E6: ='Income Statement'!E33 -> 4700 | F6: ='Income Statement'!F33 -> 5100 | G6: ='Income Statement'!G33 -> 5661 | H6: ='Income Statement'!H33 -> 6283.71 | I6: ='Income Statement'!I33 -> 6974.9181 | ... K6: ='Income Statement'!K33 -> 8439.6509
A7: Add: Provisions & Contingencies (total) | B7: ='Income Statement'!B46 -> 24100 | C7: ='Income Statement'!C46 -> 15700 | D7: ='Income Statement'!D46 -> 15800 | E7: ='Income Statement'!E46 -> 13900 | F7: ='Income Statement'!F46 -> 15000 | G7: ='Income Statement'!G46 -> 27859.448 | H7: ='Income Statement'!H46 -> 31510.621 | I7: ='Income Statement'!I46 -> 37680.087 | ... K7: ='Income Statement'!K46 -> 47345.56
A8: Operating Profit before Working Capital Changes | B8: =B5+B6+B7 -> 74222.038 | C8: =C5+C6+C7 -> 86800.47 | D8: =D5+D6+D7 -> 101805.69 | E8: =E5+E6+E7 -> 113331.85 | F8: =F5+F6+F7 -> 127107.18 | G8: =G5+G6+G7 -> 144017.74 | H8: =H5+H6+H7 -> 179530.79 | I8: =I5+I6+I7 -> 221209.33 | ... K8: =K5+K6+K7 -> 295851.09
A10: Adjustments for Working Capital
A11: (Increase) / Decrease in Investments | B11: 0 | C11: =-('Balance Sheet'!C34-'Balance Sheet'!B34) -> -293110 | D11: =-('Balance Sheet'!D34-'Balance Sheet'!C34) -> -197440 | E11: =-('Balance Sheet'!E34-'Balance Sheet'!D34) -> -95050 | F11: =-('Balance Sheet'!F34-'Balance Sheet'!E34) -> -134400 | G11: =-('Balance Sheet'!G34-'Balance Sheet'!F34) -> -238680 | H11: =-('Balance Sheet'!H34-'Balance Sheet'!G34) -> -252065.97 | I11: =-('Balance Sheet'!I34-'Balance Sheet'!H34) -> -276705.42 | J11: =-('Balance Sheet'!J34-'Balance Sheet'!I34) -> -290546.7 | K11: =-('Balance Sheet'!K34-'Balance Sheet'!J34) -> -317712.82
A12: (Increase) / Decrease in Advances | B12: 0 | C12: =-('Balance Sheet'!C39-'Balance Sheet'!B39) -> -469894.38 | D12: =-('Balance Sheet'!D39-'Balance Sheet'!C39) -> -522141.4 | E12: =-('Balance Sheet'!E39-'Balance Sheet'!D39) -> -443558.49 | F12: =-('Balance Sheet'!F39-'Balance Sheet'!E39) -> -713526.3 | G12: =-('Balance Sheet'!G39-'Balance Sheet'!F39) -> -703472.98 | H12: =-('Balance Sheet'!H39-'Balance Sheet'!G39) -> -766844.9 | I12: =-('Balance Sheet'!I39-'Balance Sheet'!H39) -> -837065.78 | J12: =-('Balance Sheet'!J39-'Balance Sheet'!I39) -> -918950.37 | K12: =-('Balance Sheet'!K39-'Balance Sheet'!J39) -> -999890.55
A13: Increase / (Decrease) in Deposits | B13: 0 | C13: ='Balance Sheet'!C15-'Balance Sheet'!B15 -> 417006 | D13: ='Balance Sheet'!D15-'Balance Sheet'!C15 -> 498000 | E13: ='Balance Sheet'!E15-'Balance Sheet'!D15 -> 415460 | F13: ='Balance Sheet'!F15-'Balance Sheet'!E15 -> 593000 | G13: ='Balance Sheet'!G15-'Balance Sheet'!F15 -> 717000 | H13: ='Balance Sheet'!H15-'Balance Sheet'!G15 -> 769580 | I13: ='Balance Sheet'!I15-'Balance Sheet'!H15 -> 858081.7 | J13: ='Balance Sheet'!J15-'Balance Sheet'!I15 -> 915162.79 | K13: ='Balance Sheet'!K15-'Balance Sheet'!J15 -> 1015830.7
A14: Increase / (Decrease) in Other Liabilities (net of other assets) | B14: 0 | C14: =('Balance Sheet'!C24-'Balance Sheet'!B24)-('Balance Sheet'!C45-'Balance Sheet'!B45) -> 301384.43 | D14: =('Balance Sheet'!D24-'Balance Sheet'!C24)-('Balance Sheet'!D45-'Balance Sheet'!C45) -> 180392.24 | E14: =('Balance Sheet'!E24-'Balance Sheet'!D24)-('Balance Sheet'!E45-'Balance Sheet'!D45) -> 65279.187 | F14: =('Balance Sheet'!F24-'Balance Sheet'!E24)-('Balance Sheet'!F45-'Balance Sheet'!E45) -> 155859.55 | G14: =('Balance Sheet'!G24-'Balance Sheet'!F24)-('Balance Sheet'!G45-'Balance Sheet'!F45) -> 140324.98 | H14: =('Balance Sheet'!H24-'Balance Sheet'!G24)-('Balance Sheet'!H45-'Balance Sheet'!G45) -> 162644.96 | I14: =('Balance Sheet'!I24-'Balance Sheet'!H24)-('Balance Sheet'!I45-'Balance Sheet'!H45) -> 146827.87 | J14: =('Balance Sheet'!J24-'Balance Sheet'!I24)-('Balance Sheet'!J45-'Balance Sheet'!I45) -> 163025.09 | K14: =('Balance Sheet'!K24-'Balance Sheet'!J24)-('Balance Sheet'!K45-'Balance Sheet'!J45) -> 148696.63
A15: Cash Generated from Operations | B15: =B8+B9+B10+B11+B12+B13+B14 -> 74222.038 | C15: =C8+C9+C10+C11+C12+C13+C14 -> 42186.517 | D15: =D8+D9+D10+D11+D12+D13+D14 -> 60616.536 | E15: =E8+E9+E10+E11+E12+E13+E14 -> 55462.539 | F15: =F8+F9+F10+F11+F12+F13+F14 -> 28040.429 | G15: =G8+G9+G10+G11+G12+G13+G14 -> 59189.741 | H15: =H8+H9+H10+H11+H12+H13+H14 -> 92844.876 | I15: =I8+I9+I10+I11+I12+I13+I14 -> 112347.71 | ... K15: =K8+K9+K10+K11+K12+K13+K14 -> 142775.04
A16: Less: Direct Taxes Paid | B16: =-'Income Statement'!B49 -> -14887.052 | C16: =-'Income Statement'!C49 -> -17001.719 | D16: =-'Income Statement'!D49 -> -20589.834 | E16: =-'Income Statement'!E49 -> -23872.425 | F16: =-'Income Statement'!F49 -> -26965.809 | G16: =-'Income Statement'!G49 -> -27845.318 | H16: =-'Income Statement'!H49 -> -35717.588 | I16: =-'Income Statement'!I49 -> -44491.691 | ... K16: =-'Income Statement'!K49 -> -60496.601
A17: NET CASH FROM OPERATING ACTIVITIES | B17: =B15+B16 -> 59334.986 | C17: =C15+C16 -> 25184.798 | D17: =D15+D16 -> 40026.702 | E17: =E15+E16 -> 31590.114 | F17: =F15+F16 -> 1074.62 | G17: =G15+G16 -> 31344.423 | H17: =H15+H16 -> 57127.288 | I17: =I15+I16 -> 67856.023 | ... K17: =K15+K16 -> 82278.442
A19: CASH FLOW FROM INVESTING ACTIVITIES
A20: Purchase of Fixed Assets (capex) | B20: 0 | C20: =-('Balance Sheet'!C44-'Balance Sheet'!B44+'Income Statement'!C33) -> -5400 | D20: =-('Balance Sheet'!D44-'Balance Sheet'!C44+'Income Statement'!D33) -> -6000 | E20: =-('Balance Sheet'!E44-'Balance Sheet'!D44+'Income Statement'!E33) -> -6500 | F20: =-('Balance Sheet'!F44-'Balance Sheet'!E44+'Income Statement'!F33) -> -7300 | G20: =-('Balance Sheet'!G44-'Balance Sheet'!F44+'Income Statement'!G33) -> -8121 | H20: =-('Balance Sheet'!H44-'Balance Sheet'!G44+'Income Statement'!H33) -> -8866.71 | I20: =-('Balance Sheet'!I44-'Balance Sheet'!H44+'Income Statement'!I33) -> -9687.0681 | J20: =-('Balance Sheet'!J44-'Balance Sheet'!I44+'Income Statement'!J33) -> -10520.167 | K20: =-('Balance Sheet'!K44-'Balance Sheet'!J44+'Income Statement'!K33) -> -11429.796
A21: Investment in Subsidiaries / Associates | B21: -1200 | C21: -1200 | D21: -1200 | E21: -1200 | F21: -1200 | G21: -1200 | H21: -1200 | I21: -1200 | J21: -1200 | K21: -1200
A22: NET CASH FROM INVESTING ACTIVITIES | B22: =B20+B21 -> -1200 | C22: =C20+C21 -> -6600 | D22: =D20+D21 -> -7200 | E22: =E20+E21 -> -7700 | F22: =F20+F21 -> -8500 | G22: =G20+G21 -> -9321 | H22: =H20+H21 -> -10066.71 | I22: =I20+I21 -> -10887.068 | ... K22: =K20+K21 -> -12629.796
A24: CASH FLOW FROM FINANCING ACTIVITIES
A25: Proceeds from Equity / QIP Issuance | B25: 0 | C25: 0 | D25: 0 | E25: 0 | F25: 25000 | G25: 0 | H25: 0 | I25: 0 | J25: 0 | K25: 0
A26: Proceeds / (Repayment) of Borrowings | B26: 0 | C26: ='Balance Sheet'!C22-'Balance Sheet'!B22 -> 28000 | D26: ='Balance Sheet'!D22-'Balance Sheet'!C22 -> 32000 | E26: ='Balance Sheet'!E22-'Balance Sheet'!D22 -> 37000 | F26: ='Balance Sheet'!F22-'Balance Sheet'!E22 -> 55000 | G26: ='Balance Sheet'!G22-'Balance Sheet'!F22 -> 48340 | H26: ='Balance Sheet'!H22-'Balance Sheet'!G22 -> 54605.4 | I26: ='Balance Sheet'!I22-'Balance Sheet'!H22 -> 61702.194 | J26: ='Balance Sheet'!J22-'Balance Sheet'!I22 -> 69743.165 | K26: ='Balance Sheet'!K22-'Balance Sheet'!J22 -> 78856.703
A27: Dividends Paid | B27: =-'Income Statement'!B60*'Income Statement'!B56 -> -6336.466 | C27: =-'Income Statement'!C60*'Income Statement'!C56 -> -10084.798 | D27: =-'Income Statement'!D60*'Income Statement'!D56 -> -12226.702 | E27: =-'Income Statement'!E60*'Income Statement'!E56 -> -14190.114 | F27: =-'Income Statement'!F60*'Income Statement'!F56 -> -15774.62 | G27: =-'Income Statement'!G60*'Income Statement'!G56 -> -17770.175 | H27: =-'Income Statement'!H60*'Income Statement'!H56 -> -22794.057 | I27: =-'Income Statement'!I60*'Income Statement'!I56 -> -28393.467 | ... K27: =-'Income Statement'!K60*'Income Statement'!K56 -> -38607.394
A28: NET CASH FROM FINANCING ACTIVITIES | B28: =B25+B26+B27 -> -6336.466 | C28: =C25+C26+C27 -> 17915.202 | D28: =D25+D26+D27 -> 19773.298 | E28: =E25+E26+E27 -> 22809.886 | F28: =F25+F26+F27 -> 64225.38 | G28: =G25+G26+G27 -> 30569.825 | H28: =H25+H26+H27 -> 31811.343 | I28: =I25+I26+I27 -> 33308.727 | ... K28: =K25+K26+K27 -> 40249.309
A30: NET INCREASE / (DECREASE) IN CASH | B30: =B17+B22+B28 -> 51798.52 | C30: =C17+C22+C28 -> 36500 | D30: =D17+D22+D28 -> 52600 | E30: =E17+E22+E28 -> 46700 | F30: =F17+F22+F28 -> 56800 | G30: =G17+G22+G28 -> 52593.248 | H30: =H17+H22+H28 -> 78871.921 | I30: =I17+I22+I28 -> 90277.682 | ... K30: =K17+K22+K28 -> 109897.95
A31: Add: Opening Cash & Cash Equivalents | B31: 175000 | C31: ='Balance Sheet'!B29+'Balance Sheet'!B30 -> 293000 | D31: ='Balance Sheet'!C29+'Balance Sheet'!C30 -> 315000 | E31: ='Balance Sheet'!D29+'Balance Sheet'!D30 -> 353000 | F31: ='Balance Sheet'!E29+'Balance Sheet'!E30 -> 387000 | G31: ='Balance Sheet'!F29+'Balance Sheet'!F30 -> 430000 | H31: ='Balance Sheet'!G29+'Balance Sheet'!G30 -> 455920 | I31: ='Balance Sheet'!H29+'Balance Sheet'!H30 -> 504481.3 | J31: ='Balance Sheet'!I29+'Balance Sheet'!I30 -> 558278.89 | K31: ='Balance Sheet'!J29+'Balance Sheet'!J30 -> 616011.69
A32: CLOSING CASH & CASH EQUIVALENTS | B32: =B30+B31 -> 226798.52 | C32: =C30+C31 -> 329500 | D32: =D30+D31 -> 367600 | E32: =E30+E31 -> 399700 | F32: =F30+F31 -> 443800 | G32: =G30+G31 -> 482593.25 | H32: =H30+H31 -> 534791.92 | I32: =I30+I31 -> 594758.98 | ... K32: =K30+K31 -> 725909.64
A33: Check: Closing Cash per Balance Sheet (Cash w/ RBI + Balances w/ Banks) | B33: ='Balance Sheet'!B29+'Balance Sheet'!B30 -> 293000 | C33: ='Balance Sheet'!C29+'Balance Sheet'!C30 -> 315000 | D33: ='Balance Sheet'!D29+'Balance Sheet'!D30 -> 353000 | E33: ='Balance Sheet'!E29+'Balance Sheet'!E30 -> 387000 | F33: ='Balance Sheet'!F29+'Balance Sheet'!F30 -> 430000 | G33: ='Balance Sheet'!G29+'Balance Sheet'!G30 -> 455920 | H33: ='Balance Sheet'!H29+'Balance Sheet'!H30 -> 504481.3 | I33: ='Balance Sheet'!I29+'Balance Sheet'!I30 -> 558278.89 | ... K33: ='Balance Sheet'!K29+'Balance Sheet'!K30 -> 679764.08

Sheet Scenarios
A1: SCENARIOS — BULL / BASE / BEAR
A2: Self-contained 5-year sensitivity to FY31E (simplified single-driver approximation — see Notes). Base case here is illustrative; the primary Base-case forecast is the full build in Income Statement / Balance Sheet.
B3: Bull | C3: Base | D3: Bear
A4: KEY ASSUMPTIONS — FY27E–FY31E (5-YEAR AVERAGE / TERMINAL)
A5: Gross Advances CAGR, FY26A–FY31E | B5: 0.155 | C5: 0.128 | D5: 0.095
A6: Domestic Net Interest Margin, FY31E | B6: 0.0335 | C6: 0.032 | D6: 0.029
A7: Non-Interest Income CAGR, FY26A–FY31E | B7: 0.14 | C7: 0.115 | D7: 0.08
A8: Cost-to-Income Ratio, FY31E | B8: 0.46 | C8: 0.485 | D8: 0.52
A9: Credit Cost, FY31E (% of gross advances) | B9: 0.0035 | C9: 0.0045 | D9: 0.0075
A10: Effective Tax Rate | B10: 0.252 | C10: 0.252 | D10: 0.252
A12: COMPUTED OUTPUTS — FY31E (self-contained 5-yr compound off FY26A base)
A13: FY31E Gross Advances (₹ cr) | B13: ='Balance Sheet'!F36*(1+B5)^5 -> 10137550 | C13: ='Balance Sheet'!F36*(1+C5)^5 -> 9006759.5 | D13: ='Balance Sheet'!F36*(1+D5)^5 -> 7764145.5
A14: FY31E Net Interest Income (₹ cr) | B14: =B13*B6 -> 339607.91 | C14: =C13*C6 -> 288216.3 | D14: =D13*D6 -> 225160.22
A15: FY31E Non-Interest Income (₹ cr) | B15: ='Revenue Model'!F65*(1+B7)^5 -> 158881.36 | C15: ='Revenue Model'!F65*(1+C7)^5 -> 142207.67 | D15: ='Revenue Model'!F65*(1+D7)^5 -> 121246.01
A16: FY31E Total Net Revenue (₹ cr) | B16: =B14+B15 -> 498489.27 | C16: =C14+C15 -> 430423.98 | D16: =D14+D15 -> 346406.23
A17: FY31E Operating Expenses (₹ cr) | B17: =B16*B8 -> 229305.06 | C17: =C16*C8 -> 208755.63 | D17: =D16*D8 -> 180131.24
A18: FY31E Operating Profit (PPOP, ₹ cr) | B18: =B16-B17 -> 269184.21 | C18: =C16-C17 -> 221668.35 | D18: =D16-D17 -> 166274.99
A19: FY31E Provisions (₹ cr) | B19: =B13*B9 -> 35481.423 | C19: =C13*C9 -> 40530.418 | D19: =D13*D9 -> 58231.091
A20: FY31E Profit Before Tax (₹ cr) | B20: =B18-B19 -> 233702.78 | C20: =C18-C19 -> 181137.93 | D20: =D18-D19 -> 108043.9
A21: FY31E Tax (₹ cr) | B21: =B20*B10 -> 58893.101 | C21: =C20*C10 -> 45646.758 | D21: =D20*D10 -> 27227.063
A22: FY31E NET PROFIT (₹ cr) | B22: =B20-B21 -> 174809.68 | C22: =C20-C21 -> 135491.17 | D22: =D20-D21 -> 80816.838
A23: FY31E EPS (₹) (shares per Income Statement, Base case) | B23: =B22/'Income Statement'!K56 -> 192.26758 | C23: =C22/'Income Statement'!K56 -> 149.02241 | D23: =D22/'Income Statement'!K56 -> 88.887855
A24: FY31E Net Profit CAGR, FY26A–FY31E | B24: =(B22/'Income Statement'!F51)^(1/5)-1 -> 0.16909605 | C24: =(C22/'Income Statement'!F51)^(1/5)-1 -> 0.1110134 | D24: =(D22/'Income Statement'!F51)^(1/5)-1 -> 0.0019302028
A25: FY31E Return on Equity (approx., vs. Base-case FY31E book equity) | B25: =B22/'Balance Sheet'!K8 -> 0.17879784 | C25: =C22/'Balance Sheet'!K8 -> 0.1385823 | D25: =D22/'Balance Sheet'!K8 -> 0.082660615

Sheet DCF Inputs
A1: DCF INPUTS
A2: State Bank of India — Inputs for Task 3 valuation (Excess Return Model, DDM & warranted P/B)
A3: (₹ crore unless stated) | B3: FY22A | C3: FY23A | D3: FY24A | E3: FY25A | F3: FY26A | G3: FY27E | H3: FY28E | I3: FY29E | J3: FY30E | K3: FY31E
A4: A. FCFE PROXY (BANK-APPROPRIATE ADAPTATION)
A5: Net Profit (PAT) | B5: ='Income Statement'!B51 -> 31634.986 | C5: ='Income Statement'!C51 -> 50198.751 | D5: ='Income Statement'!D51 -> 61115.857 | E5: ='Income Statement'!E51 -> 70859.42 | F5: ='Income Statement'!F51 -> 80041.37 | G5: ='Income Statement'!G51 -> 82651.975 | H5: ='Income Statement'!H51 -> 106018.87 | I5: ='Income Statement'!I51 -> 132062.64 | ... K5: ='Income Statement'!K51 -> 179569.28
A6: Risk-Weighted Assets (RWA) | B6: ='Balance Sheet'!B52 -> 1743629.7 | C6: ='Balance Sheet'!C52 -> 2026098 | D6: ='Balance Sheet'!D52 -> 2346247.4 | E6: ='Balance Sheet'!E52 -> 2617020 | F6: ='Balance Sheet'!F52 -> 3057840 | G6: ='Balance Sheet'!G52 -> 3497899.5 | H6: ='Balance Sheet'!H52 -> 3977636.7 | I6: ='Balance Sheet'!I52 -> 4501488.6 | ... K6: ='Balance Sheet'!K52 -> 5703709.2
A7: Increase in RWA YoY | B7: 0 | C7: =C6-B6 -> 282468.28 | D7: =D6-C6 -> 320149.4 | E7: =E6-D6 -> 270772.6 | F7: =F6-E6 -> 440820 | G7: =G6-F6 -> 440059.54 | H7: =H6-G6 -> 479737.2 | I7: =I6-H6 -> 523851.89 | J7: =J6-I6 -> 575754.34 | K7: =K6-J6 -> 626466.18
A8: Target CET1 Ratio (capital retained per unit of RWA growth) | B8: ='Balance Sheet'!B53 -> 0.0971 | C8: ='Balance Sheet'!C53 -> 0.1013 | D8: ='Balance Sheet'!D53 -> 0.1036 | E8: ='Balance Sheet'!E53 -> 0.1081 | F8: ='Balance Sheet'!F53 -> 0.114 | G8: ='Balance Sheet'!G53 -> 0.15085973 | H8: ='Balance Sheet'!H53 -> 0.15358793 | I8: ='Balance Sheet'!I53 -> 0.15874441 | ... K8: ='Balance Sheet'!K53 -> 0.17141383
A9: Less: Capital Retained to Support RWA Growth | B9: =B7*0.12 -> 0 | C9: =C7*0.12 -> 33896.194 | D9: =D7*0.12 -> 38417.928 | E9: =E7*0.12 -> 32492.712 | F9: =F7*0.12 -> 52898.4 | G9: =G7*0.12 -> 52807.145 | H9: =H7*0.12 -> 57568.464 | I9: =I7*0.12 -> 62862.227 | ... K9: =K7*0.12 -> 75175.942
A10: DISTRIBUTABLE CASH FLOW TO EQUITY (FCFE proxy) | B10: =B5-B9 -> 31634.986 | C10: =C5-C9 -> 16302.557 | D10: =D5-D9 -> 22697.929 | E10: =E5-E9 -> 38366.708 | F10: =F5-F9 -> 27142.97 | G10: =G5-G9 -> 29844.83 | H10: =H5-H9 -> 48450.407 | I10: =I5-I9 -> 69200.411 | ... K10: =K5-K9 -> 104393.33
A12: B. DIVIDEND DISCOUNT MODEL (DDM) INPUTS
A13: Dividend per Share (₹) | B13: ='Income Statement'!B60 -> 7.1 | C13: ='Income Statement'!C60 -> 11.3 | D13: ='Income Statement'!D60 -> 13.7 | E13: ='Income Statement'!E60 -> 15.9 | F13: ='Income Statement'!F60 -> 17.35 | G13: ='Income Statement'!G60 -> 19.544847 | H13: ='Income Statement'!H60 -> 25.070455 | I13: ='Income Statement'!I60 -> 31.229066 | ... K13: ='Income Statement'!K60 -> 42.463038
A14: Book Value per Share (₹) | B14: ='Balance Sheet'!B9 -> 255.34478 | C14: ='Balance Sheet'!C9 -> 300.2924 | D14: ='Balance Sheet'!D9 -> 355.07262 | E14: ='Balance Sheet'!E9 -> 418.57048 | F14: ='Balance Sheet'!F9 -> 509.04549 | G14: ='Balance Sheet'!G9 -> 580.39173 | H14: ='Balance Sheet'!H9 -> 671.92804 | I14: ='Balance Sheet'!I9 -> 785.95045 | ... K14: ='Balance Sheet'!K9 -> 1075.335
A15: Return on Equity (%) | B15: ='Income Statement'!B63 -> 0.139 | C15: ='Income Statement'!C63 -> 0.169 | D15: ='Income Statement'!D63 -> 0.2032 | E15: ='Income Statement'!E63 -> 0.1987 | F15: ='Income Statement'!F63 -> 0.1857 | G15: ='Income Statement'!G51/'Balance Sheet'!G8 -> 0.15662915 | H15: ='Income Statement'!H51/'Balance Sheet'!H8 -> 0.17354055 | I15: ='Income Statement'!I51/'Balance Sheet'!I8 -> 0.18480996 | J15: ='Income Statement'!J51/'Balance Sheet'!J8 -> 0.1859623 | K15: ='Income Statement'!K51/'Balance Sheet'!K8 -> 0.18366602
A17: C. VALUATION SCALAR INPUTS (COST OF EQUITY & TERMINAL GROWTH)
A18: Risk-Free Rate (10Y India G-Sec) | C18: 0.0665
A19: Equity Risk Premium (India) | C19: 0.0625
A20: Beta (vs. NIFTY 50, 3yr) | C20: 1.05
A21: Cost of Equity (Ke) = Rf + Beta × ERP | C21: =C18+C20*C19 -> 0.132125
A22: FY31E Explicit-Forecast ROE (memo, for reference only) | C22: =K15 -> 0.18366602
A23: Retention Ratio (1 − Dividend Payout, memo) | C23: =1-Assumptions!K41 -> 0.785
A24: Terminal Sustainable ROE (normalized, below explicit-period ROE — input) | C24: 0.16
A25: Terminal Growth Rate (g) — capped near long-run nominal GDP growth (input) | C25: 0.07
A26: Check: Ke − g must be positive for the model to be valid | C26: =C21-C25 -> 0.062125
A28: D. WARRANTED (JUSTIFIED) PRICE-TO-BOOK & FAIR VALUE
A29: Warranted P/B = (ROE − g) / (Ke − g) | C29: =(C24-C25)/(C21-C25) -> 1.4486922
A30: FY27E Book Value per Share (₹) (roll-forward anchor) | C30: =G14 -> 580.39173
A31: Implied Fair Value per Share (₹) = Warranted P/B × FY27E BVPS | C31: =C29*C30 -> 840.80895
A32: Current Share Price (₹, 25-Sep-2026) | C32: 983
A33: Implied Upside / (Downside) % | C33: =C31/C32-1 -> -0.1446501

Sheet Valuation
A1: VALUATION SUMMARY — STATE BANK OF INDIA
A2: Excess Return / Warranted P/B (DCF Inputs tab) blended with trading comparables; football-field & price target.
A4: A. EXCESS RETURN / WARRANTED P/B VALUATION (from DCF Inputs)
A5: Cost of Equity (Ke) | B5: ='DCF Inputs'!C21 -> 0.132125
A6: Terminal Sustainable ROE | B6: ='DCF Inputs'!C24 -> 0.16
A7: Terminal Growth Rate (g) | B7: ='DCF Inputs'!C25 -> 0.07
A8: Warranted P/B | B8: ='DCF Inputs'!C29 -> 1.4486922
A9: FY27E Book Value per Share (₹) | B9: ='DCF Inputs'!C30 -> 580.39173
A10: Implied Fair Value — Excess Return Model (₹) | B10: ='DCF Inputs'!C31 -> 840.80895
A12: B. SENSITIVITY — IMPLIED FAIR VALUE (₹) BY Ke AND TERMINAL GROWTH (g)
A13: (Rows = Cost of Equity; Columns = Terminal Growth; Terminal ROE fixed per DCF Inputs)
A14: Ke \ g | B14: 0.055 | C14: 0.06 | D14: 0.065 | E14: 0.07 | F14: 0.075 | G14: 0.08
A15: 0.112 | B15: =(('DCF Inputs'!$C$24-B$14)/($A15-B$14))*'DCF Inputs'!$C$30 -> 1069.1427 | C15: =(('DCF Inputs'!$C$24-C$14)/($A15-C$14))*'DCF Inputs'!$C$30 -> 1116.1379 | D15: =(('DCF Inputs'!$C$24-D$14)/($A15-D$14))*'DCF Inputs'!$C$30 -> 1173.1322 | E15: =(('DCF Inputs'!$C$24-E$14)/($A15-E$14))*'DCF Inputs'!$C$30 -> 1243.6966 | F15: =(('DCF Inputs'!$C$24-F$14)/($A15-F$14))*'DCF Inputs'!$C$30 -> 1333.3324 | G15: =(('DCF Inputs'!$C$24-G$14)/($A15-G$14))*'DCF Inputs'!$C$30 -> 1450.9793
A16: 0.122 | B16: =(('DCF Inputs'!$C$24-B$14)/($A16-B$14))*'DCF Inputs'!$C$30 -> 909.56913 | C16: =(('DCF Inputs'!$C$24-C$14)/($A16-C$14))*'DCF Inputs'!$C$30 -> 936.1157 | D16: =(('DCF Inputs'!$C$24-D$14)/($A16-D$14))*'DCF Inputs'!$C$30 -> 967.31956 | E16: =(('DCF Inputs'!$C$24-E$14)/($A16-E$14))*'DCF Inputs'!$C$30 -> 1004.5242 | F16: =(('DCF Inputs'!$C$24-F$14)/($A16-F$14))*'DCF Inputs'!$C$30 -> 1049.6446 | G16: =(('DCF Inputs'!$C$24-G$14)/($A16-G$14))*'DCF Inputs'!$C$30 -> 1105.5081
A17: 0.132125 | B17: =(('DCF Inputs'!$C$24-B$14)/($A17-B$14))*'DCF Inputs'!$C$30 -> 790.16054 | C17: =(('DCF Inputs'!$C$24-C$14)/($A17-C$14))*'DCF Inputs'!$C$30 -> 804.70258 | D17: =(('DCF Inputs'!$C$24-D$14)/($A17-D$14))*'DCF Inputs'!$C$30 -> 821.41102 | E17: =(('DCF Inputs'!$C$24-E$14)/($A17-E$14))*'DCF Inputs'!$C$30 -> 840.80895 | F17: =(('DCF Inputs'!$C$24-F$14)/($A17-F$14))*'DCF Inputs'!$C$30 -> 863.60258 | G17: =(('DCF Inputs'!$C$24-G$14)/($A17-G$14))*'DCF Inputs'!$C$30 -> 890.76909
A18: 0.142 | B18: =(('DCF Inputs'!$C$24-B$14)/($A18-B$14))*'DCF Inputs'!$C$30 -> 700.47278 | C18: =(('DCF Inputs'!$C$24-C$14)/($A18-C$14))*'DCF Inputs'!$C$30 -> 707.7948 | D18: =(('DCF Inputs'!$C$24-D$14)/($A18-D$14))*'DCF Inputs'!$C$30 -> 716.06772 | E18: =(('DCF Inputs'!$C$24-E$14)/($A18-E$14))*'DCF Inputs'!$C$30 -> 725.48967 | F18: =(('DCF Inputs'!$C$24-F$14)/($A18-F$14))*'DCF Inputs'!$C$30 -> 736.31787 | G18: =(('DCF Inputs'!$C$24-G$14)/($A18-G$14))*'DCF Inputs'!$C$30 -> 748.89256
A19: 0.152 | B19: =(('DCF Inputs'!$C$24-B$14)/($A19-B$14))*'DCF Inputs'!$C$30 -> 628.25909 | C19: =(('DCF Inputs'!$C$24-C$14)/($A19-C$14))*'DCF Inputs'!$C$30 -> 630.86058 | D19: =(('DCF Inputs'!$C$24-D$14)/($A19-D$14))*'DCF Inputs'!$C$30 -> 633.76109 | E19: =(('DCF Inputs'!$C$24-E$14)/($A19-E$14))*'DCF Inputs'!$C$30 -> 637.01532 | F19: =(('DCF Inputs'!$C$24-F$14)/($A19-F$14))*'DCF Inputs'!$C$30 -> 640.69217 | G19: =(('DCF Inputs'!$C$24-G$14)/($A19-G$14))*'DCF Inputs'!$C$30 -> 644.8797
A21: Current price ₹983 shown for reference in the football field (section E) below.
A23: C. COMPARABLE-COMPANIES VALUATION (from Comparable Companies tab)
A24: Implied Price — Peer Median P/E × SBI FY27E EPS | B24: ='Comparable Companies'!D24 -> 1209.0533
A25: Implied Price — Peer Median P/B × SBI FY27E BVPS | B25: ='Comparable Companies'!D25 -> 969.25419
A26: Average of P/E- and P/B-implied Comps Valuation (₹) | B26: =AVERAGE(B24:B25) -> 1089.1538
A28: D. VALUATION SUMMARY & WEIGHTED PRICE TARGET
A29: Method | B29: Low (₹) | C29: Base (₹) | D29: High (₹) | E29: Weight (%) | F29: Weighted (₹)
A30: Excess Return / Warranted P/B | B30: =B10*0.9 -> 756.72805 | C30: =B10 -> 840.80895 | D30: =B10*1.1 -> 924.88984 | E30: 0.55 | F30: =C30*E30 -> 462.44492
A31: Trading Comparables (P/E & P/B blend) | B31: =MIN(B24:B25) -> 969.25419 | C31: =B26 -> 1089.1538 | D31: =MAX(B24:B25) -> 1209.0533 | E31: 0.45 | F31: =C31*E31 -> 490.11919
A32: Precedent Transactions | B32: n/a | C32: n/a | D32: n/a | E32: 0 | F32: 0 | G32: Not used: SBI is systemically important and majority state-owned; bank-M&A control premia are not a meaningful reference point for its equity valuation.
A33: WEIGHTED AVERAGE PRICE TARGET | E33: =SUM(E30:E32) -> 1 | F33: =SUM(F30:F32) -> 952.56411
A35: Rounded 12-Month Price Target (₹) | B35: =MROUND(F33,5) -> 955
A36: Current Share Price (₹, 25-Sep-2026) | B36: 983
A37: Implied Upside / (Downside) to Target | B37: =B35/B36-1 -> -0.028484232
A38: Recommendation | B38: =IF(B37>0.15,"BUY",IF(B37>=-0.05,"HOLD","SELL")) -> HOLD
A40: E. VALUATION FOOTBALL FIELD (LOW / BASE / HIGH, ₹ PER SHARE)
A41: Method | B41: Low | C41: Base | D41: High
A42: Excess Return / Warranted P/B | B42: =B30 -> 756.72805 | C42: =C30 -> 840.80895 | D42: =D30 -> 924.88984
A43: Trading Comparables | B43: =B31 -> 969.25419 | C43: =C31 -> 1089.1538 | D43: =D31 -> 1209.0533
A44: Current Price (memo) | B44: =B36 -> 983 | C44: =B36 -> 983 | D44: =B36 -> 983
A46: F. KEY CATALYSTS & RISKS TO PRICE TARGET
A47: 1. YONO 2.0 execution — successful repositioning as customers' primary payments/transaction surface would defend fee income and the CASA franchise.
A48: 2. NIM recovery — domestic NIM troughed near 3.0% in FY26; deposit repricing and the Sept-2025 CRR cut should lift margins back toward ~3.2% through FY27-28.
A49: 3. Continued asset-quality cleanup — GNPA/NNPA at multi-decade lows (1.49%/0.39%); further improvement would support re-rating toward private-peer multiples.
A50: 4. Subsidiary value unlock — the planned SBI Funds Management stake-sale IPO would crystallize and make visible SOTP value not reflected in the standalone P/B.
A51: 5. PSU-bank sector re-rating — SBI trades at ~1.5x P/B vs. ~1.9x median for large private banks despite comparable or better ROE; narrowing this gap is a structural catalyst.
A53: 1. Government-directed lending / policy risk — priority-sector mandates and periodic moral suasion on rates can pressure margins independent of market conditions.
A54: 2. NIM undershoot — if deposit repricing lags further or rate cuts continue, NIM recovery could disappoint, compressing the earnings base the target relies on.
A55: 3. Credit-cycle normalization — SME/agri/unsecured-retail segments driving recent growth are also the most cycle-sensitive; a sharper slowdown would reverse recent slippage improvements.
A56: 4. Execution risk on YONO 2.0 — failure to shift meaningful transaction volume onto the platform cedes ground to UPI-native fintechs without an offsetting cost benefit.
A57: 5. Treasury / one-off dependency — a meaningful share of recent reported profit growth (Yes Bank stake sale, treasury gains) is non-recurring; normalization could slow headline EPS growth.

Sheet Comparable Companies
A1: COMPARABLE COMPANIES ANALYSIS
A2: Peer set: large-cap Indian banks (private + PSU). Market data as of late Sept 2026. P/E and P/B are the standard bank valuation multiples (EV/EBITDA is not meaningful for a bank since deposits/advances, not debt/capex, drive its balance sheet).
A3: Company | B3: Price (₹) | C3: Mkt Cap (₹cr) | D3: P/E (x) | E3: P/B (x) | F3: ROE (%) | G3: Type | H3: Peer rationale
A4: HDFC Bank | B4: 737.25 | C4: 1398000 | D4: 14.98 | E4: 1.87 | F4: 0.1249 | G4: Private | H4: Largest private bank; scale/franchise benchmark post-HDFC Ltd merger
A5: ICICI Bank | B5: 1422.8 | C5: 1022835 | D5: 18.24 | E5: 2.74 | F5: 0.1502 | G5: Private | H5: 2nd-largest private bank; highest NIM among large peers, strong digital platform
A6: Axis Bank | B6: 1210.75 | C6: 387515 | D6: 13.3 | E6: 1.67 | F6: 0.1326 | G6: Private | H6: 3rd-largest private bank; corporate & SME-banking strength
A7: Kotak Mahindra Bank | B7: 413.1 | C7: 411842 | D7: 20.29 | E7: 2.21 | F7: 0.1089 | G7: Private | H7: Premium-rated private bank; conservative underwriting, high margins
A8: Punjab National Bank | B8: 104.5 | C8: 125000 | D8: 7 | E8: 0.84 | F8: 0.124 | G8: PSU | H8: 2nd-largest PSU bank; closest PSU-peer analogue to SBI
A9: Bank of Baroda | B9: 276.9 | C9: 144359 | D9: 7.21 | E9: 0.87 | F9: 0.1164 | G9: PSU | H9: 3rd-largest PSU bank; similar international-banking footprint
A10: Canara Bank | B10: 129.5 | C10: 114200 | D10: 6.39 | E10: 1.03 | F10: 0.161 | G10: PSU | H10: Large PSU peer; comparable priority-sector mix and ownership structure
A11: State Bank of India (Target) | B11: 983 | C11: 903216 | D11: 10.9 | E11: 1.47 | F11: 0.1857 | G11: PSU (Target) | H11: Largest bank in India by every balance-sheet metric; subject of this coverage initiation
A13: STATISTICAL SUMMARY (peer set only, excl. SBI)
A14: Maximum | D14: =MAX(D4:D10) -> 20.29 | E14: =MAX(E4:E10) -> 2.74 | F14: =MAX(F4:F10) -> 0.161
A15: 75th Percentile | D15: =QUARTILE(D4:D10,3) -> 16.61 | E15: =QUARTILE(E4:E10,3) -> 2.04 | F15: =QUARTILE(F4:F10,3) -> 0.1414
A16: Median | D16: =MEDIAN(D4:D10) -> 13.3 | E16: =MEDIAN(E4:E10) -> 1.67 | F16: =MEDIAN(F4:F10) -> 0.1249
A17: 25th Percentile | D17: =QUARTILE(D4:D10,1) -> 7.105 | E17: =QUARTILE(E4:E10,1) -> 0.95 | F17: =QUARTILE(F4:F10,1) -> 0.1202
A18: Minimum | D18: =MIN(D4:D10) -> 6.39 | E18: =MIN(E4:E10) -> 0.84 | F18: =MIN(F4:F10) -> 0.1089
A20: APPLY PEER MULTIPLES TO SBI
A21: SBI FY27E EPS (₹, per Income Statement) | D21: ='Income Statement'!G58 -> 90.906264
A22: SBI FY27E BVPS (₹, per Balance Sheet) | D22: ='Balance Sheet'!G9 -> 580.39173
A24: Implied Price — Peer Median P/E × SBI FY27E EPS | D24: =D16*D21 -> 1209.0533
A25: Implied Price — Peer Median P/B × SBI FY27E BVPS | D25: =E16*D22 -> 969.25419
A27: Rationale: SBI's FY26 ROE (18.6%) sits above the PSU-peer median and close to the private-bank median, while its P/B (1.47x) trades at roughly half the private-bank median (~1.9x) — supporting the view that SBI's re-rating toward private-peer multiples is not yet complete. No premium/discount adjustment is applied to the raw peer-median multiples above; the Valuation tab blends this comps view with the Excess Return / Warranted P/B output.

Sheet Charts
A1: CHARTS — STATE BANK OF INDIA INITIATING COVERAGE
A2: All charts are native, editable Excel charts built directly from the model's Revenue Model, Income Statement, Balance Sheet, Cash Flow Statement, Scenarios, DCF Inputs, Comparable Companies and Valuation tabs — updating automatically if any input changes.
B4: 1. BALANCE SHEET GROWTH, SEGMENT & GEOGRAPHY MIX
B5: Chart 1. Gross Advances by Segment — Stacked Area (₹ cr) | J5: Chart 2. Gross Advances by Geography — Stacked Bar (₹ cr)
B24: Chart 3. Deposit Mix — CASA vs. Term Deposits, Stacked Bar (₹ cr) | J24: Chart 4. Total Advances & Deposits Trend (₹ cr)
B43: 2. MARGINS, ASSET QUALITY & CAPITAL ADEQUACY
B44: Chart 5. Domestic Net Interest Margin Trend (%) | J44: Chart 6. Cost-to-Income Ratio Trend (%)
B63: Chart 7. Asset Quality — Gross & Net NPA Ratio Trend (%) | J63: Chart 8. Provision Coverage Ratio Trend (%)
B82: Chart 9. Capital Adequacy — CET1 / Tier 1 / CAR Trend (%) | J82: Chart 10. CASA Ratio Trend (%)
B101: 3. PROFITABILITY, RETURNS & PER-SHARE METRICS
B102: Chart 11. Net Profit (PAT) Trend — Bar (₹ cr) | J102: Chart 12. Basic EPS Trend — Bar (₹)
B121: Chart 13. Return on Assets (ROA) & Return on Equity (ROE) Trend (%) | J121: Chart 14. Dividend per Share & Book Value per Share (₹)
B140: Chart 15. Non-Interest Income Composition — Stacked Bar (₹ cr) | J140: Chart 16. Operating Expense Composition — Stacked Bar (₹ cr)
B159: Chart 17. Total Net Revenue & Operating Profit (PPOP) Trend (₹ cr) | J159: Chart 18. Distributable Cash Flow to Equity (FCFE proxy) Trend (₹ cr)
B178: 4. SCENARIO ANALYSIS — BULL / BASE / BEAR (FY31E)
B179: Chart 19. FY31E Net Profit by Scenario — Bar (₹ cr) | J179: Chart 20. FY31E EPS by Scenario — Bar (₹)
B198: Chart 21. FY31E Gross Advances by Scenario (₹ cr) | J198: Chart 22. FY31E Return on Equity by Scenario (%)
B217: 5. VALUATION — DCF SENSITIVITY, COMPARABLES & FOOTBALL FIELD
B218: Chart 23. DCF Sensitivity — Fair Value (₹) vs. Cost of Equity, by Terminal Growth ⭐ | J218: Chart 24. Valuation Football Field — Low / Base / High (₹) ⭐
B237: Chart 25. Peer P/E Comparison (x) | J237: Chart 26. Peer P/B Comparison (x)
B256: Chart 27. ROE vs. P/B Positioning — Scatter | J256: Chart 28. Peer Market Capitalization Comparison (₹ cr)
B275: Chart 29. 12-Month Price Target vs. Current Price (₹)

Sheet Notes
A1: NOTES, SOURCES & MODELING CONVENTIONS
A4: COLOR CODE
A5: Blue text = hardcoded input (historical actual, or a projection assumption you can change)
A6: Black text = formula calculated within the same sheet
A7: Green text = formula linking to a cell on another sheet
A8: Navy/gold fill in year header = actuals (FY22A–FY26A) vs. estimates (FY27E–FY31E)
A10: PERIODS & CONVENTIONS
A11: Fiscal year end = March 31 (e.g., FY26A = year ended 31 March 2026).
A12: All figures are STANDALONE (parent bank only), not consolidated, unless stated. Consolidated figures (which include SBI Life, SBI Cards, SBI General, SBI Mutual Fund, etc.) are higher for net profit, book value and EPS — e.g., consolidated FY26 net profit and TTM EPS reported by market-data vendors will exceed the standalone figures modeled here. This is a deliberate choice: the operating model focuses on the core bank, and subsidiary value is addressed separately (sum-of-the-parts) in Task 3 valuation.
A13: Interest income/expense on advances, investments, deposits and borrowings is calculated on CLOSING balances × yield/cost, a simplification versus average-balance methodology; this is standard practice in initiating-coverage models and does not materially affect trend conclusions.
A14: Balance Sheet 'Other Assets' is the residual balancing plug (Total Liabilities less all other modeled asset lines) so the balance sheet ties out exactly in every period — advances, investments, deposits and capital are each modeled independently off disclosed/assumed drivers rather than derived residually.
A16: KEY DATA SOURCES (Task 1 research, cross-checked against company disclosures)
... A55: Native, editable Excel charts (not images) on a dedicated 'Charts' tab and alongside relevant data, covering advances/deposits trends, NIM, asset quality, profitability, per-share metrics and scenario comparisons.
